{
  "name" : "72939fa12d337521e893.pdf",
  "metadata" : {
    "source" : "META",
    "title" : "Data Opportunities for Studying the Sexual and Reproductive Health of Immigrants in the United States",
    "authors" : [ ],
    "emails" : [ ],
    "sections" : [ {
      "heading" : null,
      "text" : "This paper aims to identify, review, and evaluate publicly available national- and local-level data sources that collect information on the sexual and reproductive health (SRH) of immigrants in the United States. We review public-use sources from the last 30 years that include information on immigration, SRH, health service utilization, and race/ethnicity. For each source, we evaluated the strengths and challenges of the study design and content as they relate to studying immigrant SRH. We identified and reviewed 22 national and seven local sources. At the national level, the National Longitudinal Study of Adolescent to Adult Health and the National Survey of Family Growth contained the most information; at the local level, the New York City Community Health Survey was the most robust. These sources present opportunities to advance research, improve public health surveillance, and inform policies and programs related to the SRH of this rapidly growing and often underserved population.\nKeywords\nImmigrants; sexual health; reproductive health; database\nSince the passing of the Immigration and Nationality Act of 1965, the share of the United States population that was not born in the country has grown from 9.6 million or 5% of the total population to a record estimated population of 43.7 million (or 14%) in 2016.1,2 The foreign-born population lives in every state in the country, with over half living in California, New York, Texas, and Florida.3 (In this paper, we refer to the foreign-born population as immigrants.) With the rapid growth of the immigrant population and the country’s changing political climate, researchers and advocates alike have called for more research on the health behaviors, needs, and outcomes of immigrants.4–7 Literature suggests that immigrants, broadly, have better birth and maternal health outcomes and lower overall mortality rates than the U.S.-born population.8,9 At the same time, their access to health care is often challenged due to lower rates of health insurance coverage, lack of familiarity with the health system, and linguistic barriers.8,9 Despite the vast heterogeneity of the immigrant population, research rarely disaggregates immigrant data by factors such as race/ethnicity or\nPlease address all correspondence to Athena Tapales, Guttmacher Institute, 125 Maiden Lane, 7th Fl., New York, NY 10038.\nuthor M anuscript\nA uthor M anuscript A uthor M anuscript\nlength of stay.5–7 Furthermore, the sexual and reproductive health (SRH) of many immigrant groups is not well-documented in the current public health literature. Research in the immigrant population has been constrained by data limitations, particularly at the subgroup level. Few data sources collect disaggregated race/ethnicity data for subgroup analyses, provide comparable definitions of immigration status across surveys, use multilingual survey tools, and/or employ methodological techniques such as oversampling immigrants or linking individual- and population-level data sources to facilitate analyses.4,5,10,11 Consequently, we do not know the extent to which many SRH measures differ by nativity status (foreignversus U.S.-born) and between ethnic subgroups. Race and ethnicity data are particularly important given that they provide additional depth and context to the immigrant experience of specific groups. Other facets of nativity status may also influence SRH and health care access, including length of stay, language skills, and documentation status.12–18 Cumulatively, these factors may influence immigrants’ ability to seek out health resources and navigate the health system. In fact, small-scale studies suggest that immigrant women are less likely to seek out SRH-related cancer screenings.19–21 Additionally, existing literature suggests that outcomes and behaviors vary by immigrant generation. For example, for a variety of health indicators, the protective immigrant health effect decreases with each subsequent generation.22 However, less is known about how SRH measures change from one generation to the next since data across immigrant generations are typically unavailable.\nIn order to develop effective, evidence-based programs and policies that support immigrant SRH, additional research is needed. The goal of this paper is to review and summarize existing publicly-available quantitative data sources that include information on nativity status, race/ethnicity, SRH behaviors and outcomes, and health care utilization. We focus on national datasets and highlight select local data sources as these may be more responsive to research questions at the state and city levels. We evaluate the information collected for each data source, propose recommendations to address existing data challenges, and highlight opportunities to advance future study of immigrant SRH. This article should serve as a resource for researchers and advocates interested in further supporting the SRH of immigrant populations in the U.S. by using robust data to inform the policy and programmatic decisions made on behalf of these populations.\nMethods\nData sources are included in this review if they are publicly available and contain at least 1) one measure of immigration, 2) one measure of sexual and/or reproductive health, and 3) data collected between 1987 and 2017. We focus on sources from the last 30 years because demographic trends show that immigrant populations in the U.S. have rapidly and steadily increased within this time frame.1 We examine data sources into two categories: national level and local level (i.e., state, county, and city data). To identify national-level data, we reviewed publicly-available data sources from select federal agencies such as the Centers for Disease Control and Prevention, the U.S. Census Bureau, and the Bureau of Labor Statistics, as well as academic institutions such as the UNC Carolina Population Center and Princeton University. Eligible local-level surveys were identified by focusing on data sources from states with the largest immigrant populations, including California, Texas, New York, Florida, New Jersey, Illinois, and Massachusetts.2 We identify only a shortlist of these local\nJ Health Care Poor Underserved. Author manuscript; available in PMC 2019 August 13.\nA uthor M anuscript A uthor M anuscript\nA uthor M anuscript A uthor M anuscript\ndata sources, primarily from state departments of health, to provide examples of the utility of non-national data in assessing immigrant SRH. In contrast, we aim to provide a comprehensive list of relevant national-level data sources.\nFor each data source included in this review, we provide a brief description of the survey, including its aims, design, and sample size. As a point of reference, we also provide an example publication that uses the data source. We identify measures of immigration, race and ethnicity, SRH, and health service utilization. Each of these categories is detailed below.\nSurvey aims and design.\nFor each data source, we include its full name, the affiliated research institution, and a summary of the survey’s main purpose. We also indicate the timeframe covered by the data source, the number of survey waves or rounds, and the intervals at which they occurred. Throughout this paper, we refer to most data sources by their acronyms, which are spelled out in Tables 1 and 2. We indicate the survey design (e.g., cross-sectional or longitudinal), population, sampling frame (e.g., neighborhoods, households, clinics), and the representativeness of the sample. Each survey that we included is conducted in languages other than English.\nSample size.\nWe include the rounded sample size from the most recent data available at the time of this review and any oversampling that occurred. We also report the number of women aged 15– 44 and the foreign-born sample from the data source’s website and/or codebook, when available. Although imprecise, these figures can provide a sense of the number of immigrant women of reproductive age (15–44) in the sample. All reported sample sizes, unless otherwise indicated, are rounded to the nearest hundred and include both men and women.\nSample publication.\nFor each data source, we include a published study as an example of quantitative research that uses the corresponding data to study immigrant health. When possible, we list articles specifically about immigrant SRH.\nImmigration.\nWe identify measures of immigration related to immigrant status and context such as nativity (i.e., born in or outside of the U.S.), citizenship, documentation (e.g., green card or visa status), length of stay in the U.S., year/age of entry, country or region of birth, and language spoken at home.\nRace and ethnicity.\nWe report racial categories from each of the surveys using the 2015 guidelines issued by the Office of Management and Budget (OMB).23 The OMB recommends that the minimum standard for measures of race should include the distinct categories of American Indian or Alaska Native, Asian, Black or African American, Native Hawaiian or other Pacific Islander, and White. For ethnicity, although the OMB minimum standard only includes Hispanic/ Latino and non-Hispanic/Latino origin, we highlight additional ethnicity information when\nJ Health Care Poor Underserved. Author manuscript; available in PMC 2019 August 13.\nA uthor M anuscript A uthor M anuscript\nA uthor M anuscript A uthor M anuscript\nprovided. In surveys that collected this additional information, ethnicity categories typically reflected regions or countries of origin (e.g., Chinese, Ethiopian). We also identify data sources that report on ancestry, a component of immigrant history and potential identifier of ethnicity or country of origin.\nSexual and reproductive health.\nThis review focuses on the following six SRH domains, each representing multiple measures of SRH: (1) pregnancy intention (i.e., wantedness of past, current, or future pregnancy), (2) fertility history (e.g., number of births or children, maternal age at first birth, history of abortion, and other pregnancy outcomes), (3) contraceptive use (e.g., current method(s) used and history of method use), (4) HIV/STI history (e.g., history of HIV/STI testing or treatment, HPV vaccination, and STI diagnoses), (5) sexual behavior (e.g., age at first sexual encounter, timing of last sexual encounter, and other information about sexual encounters), and (6) sexual orientation.\nHealth service utilization.\nWe also examine each data source for two key domains of health service utilization: health insurance status and source of care. Source of care typically assesses the type of health provider visited for services, such as private doctor, public clinic, hospital, or urgent care. Follow-up questions related to each source of care may include the type and quality of care provided. This information is important when considering if and how immigrant populations access health services generally and SRH care specifically.\nResults\nData sources and sample size.\nBased on the selection criteria described earlier, we identified 29 publicly available data sources that collected data on immigration, race/ethnicity, SRH, and health service utilization. Table 1 reports on 22 publicly available nationally representative data sources, including 14 longitudinal and eight cross-sectional surveys. We identified the immigrant sample size in the most recent rounds of 14 of these data sources. Three surveys (National Survey of Reproductive and Contraceptive Knowledge [Fog Zone],24 Panel Study of Income Dynamics [PSID]—Child Development Survey [CDS],25 and National Longitudinal Survey of Youth [NLSY97]26) had fewer than 500 immigrants in their most recent samples. Another three (National Longitudinal Survey of Youth [NLSY79],27 Fragile Families and Child Wellbeing Study [FFCWS],28 and Panel Study of Income Dynamics [PSID]—Individual and Family Data [Main]29) surveyed 500–1,000 immigrants. Four surveys (National Longitudinal Study of Adolescent to Adult Health [Add Health],30 Abortion Patient Survey [APS],31 National Survey of Family Growth [NSFG],32 National Survey of Families and Households [NSFH],33 and National Health and Nutrition Examination Survey [NHANES]34) included 1,000–2,000 immigrants in their samples. Three surveys had sample sizes as large as 13,000 (Current Population Survey [CPS]35), 18,000 (National Health Interview Survey [NHIS]36), and 82,000 (American Community Survey [ACS]37). Note that some of these surveys have multiple waves of data; in these cases, pooling waves of data would further increase the sample size of immigrants.\nJ Health Care Poor Underserved. Author manuscript; available in PMC 2019 August 13.\nA uthor M anuscript A uthor M anuscript\nA uthor M anuscript A uthor M anuscript\nWe also identified seven examples of (1) state-level data from New York and California (Pregnancy Risk Assessment Monitoring System [PRAMS],38 California Health Interview Survey [CHIS]39, California Women’s Health Survey [CWHS],40 and California Maternal Infant Health Assessment [MIHA]41); (2) county-level data from Los Angeles (LA County Health Survey [LACHS]42); and (3) city-level data from El Paso (Border Contraceptive Access Study [BCAS]43) and New York City (New York City Community Health Survey [NYCCHS]44) (Table 2). Six surveys are cross-sectional and all but one (BCAS) are representative of their target population. The BCAS is also longitudinal in design. We identified the immigrant sample size in three of the local data sources; these ranged from approximately 700 foreign-born respondents in BCAS to 4,000 or more in the NYC CHS and CHIS.\nImmigration.\nAt a national level, with the exception of five surveys (National Vital Statistics System: Birth Data [NVSS—Birth Data],45 National Longitudinal Survey of Youth [NLSY79 Child/YA],46 PSID-CDS, Panel Study of Income Dynamics [PSID]—Child Development Survey 2014 [CDS-2014],47 Panel Study of Income Dynamics [PSID]—Transition to Adulthood Supplement [TAS],48) all data sources included at least two measures of immigration. The most common were nativity (included in 19 surveys), language spoken at home, country or region of birth, and year of entry (each in 13 surveys) (Table 3). Fourteen data sources (Add Health, CPS, Early Childhood Longitudinal Study—Birth cohort [ECLS-B],49 Early Childhood Longitudinal Study—Kindergarten [ECLS-K],50 FFCWS, NHANES, New Immigrant Survey [NIS],51 NLSY79, NLSY79 Child/YA, NLSY97, NSFH, PSID-Main, and Survey of Income and Program Participation [SIPP]52, NVSS) collected additional data on respondents’ parents’ country of birth, year of entry, citizenship, and language spoken at home, allowing for research on second-generation immigrants. Without information about parents’ country of birth, it is difficult to determine second generation status, which is defined as being born in the U.S. to foreign-born parents (first-generation immigrants). The NIS, NLSY-79, and PSID-Main collected data on documentation status.\nAt the state and county level, all seven data sources included at least two measures of immigration; the most commonly collected data were on country of birth, length of stay, and language(s) spoken at home, each included in five surveys (Table 4). The CHIS included the most measures of immigration, including citizenship, language spoken at home, length of stay, country of birth, and documentation status. Four surveys (CHWS, NYC CHS, PRAMS, and BCAS) included a measure of nativity and only NYC CHS and BCAS asked about parents’ nativity (Table 4).\nRace and ethnicity.\nApart from seven data sources (Add Health, FFCWS, NSFH, Fog Zone, PSID-CDS, BCAS, CWHS, and MIHA), all of the surveys we examined followed the basic OMB guidelines for collecting race and ethnicity data (Tables 3 and 4).23 Of these surveys that met OMB guidelines, all but another two (APS and ECLS) included two or more more detailed categories for ethnicity. Hispanic subgroups were most frequently disaggregated in comparison with other ethnic groups, followed by Asian and Pacific Islander subgroups.\nJ Health Care Poor Underserved. Author manuscript; available in PMC 2019 August 13.\nA uthor M anuscript A uthor M anuscript\nA uthor M anuscript A uthor M anuscript\nDistinctions for Asian origin focused primarily on select countries such as China, Japan, Korea, the Philippines, India, and Vietnam. Pacific Islander origins include Native Hawaiian, Guamanian, and Samoan. African and European origin were rarely disaggregated. Seven surveys at the national level (ACS, Add Health, FFCWS, NHANES, NLSY-79, NLSY-79 Child/YA, and PSID-Main) and three at the local level (CHIS, LACHS, NYC CHS) had a measure of self-reported ancestry (Tables 3 and 4).\nSexual and reproductive health and health service utilization.\nWith the exception of six data sources (ACS, CPS, ECLS-K, NIS, SIPP, and NVSS), all of the included national surveys collected data on two or more SRH domains relevant to this review (Table 3). The most common domain measured was fertility history; in contrast, data on sexual orientation was collected by only four data sources (NHANES, NHIS, Add Health, and NSFG surveys). All of the surveys except the NSFH collected information on health service utilization. Overall, the NSFG and Add Health, followed by NHANES, NHIS, and the Fog Zone, collected the most detailed information across multiple SRH domains and on health care utilization.\nAt the state, county, and city level, each of the seven data sources included measures of at least two SRH domains; the most common were pregnancy intention, contraceptive use, and sexual behavior, addressed in at least four of seven surveys (Table 4). Five of the seven surveys collected information on health insurance status and source of care. Overall, the CWHS and NYC CHS contained the most information related to SRH and health care utilization.\nIn general, at the national level, Add Health and NSFG contained the most detailed information on immigration and SRH, followed by NHANES, NHIS, and PSID (Table 3). In contrast, NSFH and NVSS collected the least information on immigration and SRH. At the state and county level, the NYC CHS included the most information for both SRH and immigration, followed by CWHS and CHIS; however, CHIS included more information on immigration (compared with SRH) whereas CWHS collected notably more data on SRH than immigration (Table 4).\nNotably, questions that measured immigration, SRH, and health service utilization varied between data sources. In some cases, questions varied between survey wave, as a result of evolving categories and definitions of particular measures. Similarly, the breadth and depth of available SRH information often varied between data sources depending on the purpose of the data source, with some including SRH-related questions in optional modules rather than mandatory core sections of a survey.\nDiscussion\nThis analysis identifies national-, state- and local-level data sources that can facilitate further examination of immigrant SRH. We highlight large publicly-available data sources with notable immigrant sample sizes and key information on immigration and SRH to encourage broader use of these data. At the same time, we note potential challenges across data sources. For example, despite being publicly available, some data sources restricted access\nJ Health Care Poor Underserved. Author manuscript; available in PMC 2019 August 13.\nA uthor M anuscript A uthor M anuscript\nA uthor M anuscript A uthor M anuscript\nto disaggregated data by ethnicity due to small sample sizes; however, organizations such as the National Center for Health Statistics can grant access to these restricted data after an application process, allowing for subgroup analyses. The type of information on immigration, race and ethnicity, and SRH also varied between data sources and over time. Race/ethnicity categories also change over time, often reflective of shifting OMB guidelines, and measures of immigration may vary based on published literature identifying new characteristics of the immigrant context. In these cases, pooled analyses across survey waves or surveillance of SRH outcomes over time can be challenging. Furthermore, few data sources collect detailed data on both immigration and SRH, suggesting that researchers may face a trade-off in each data source. Despite these potential challenges, the data sources presented in this paper are critical to initiating and advancing much-needed research on immigrant SRH.\nLimitations.\nThis study has several limitations. Although we attempt to provide a far-reaching list of data sources relevant to the study of immigrant SRH, this paper is not intended as a formal systematic review, so neither the national nor local lists are exhaustive. We also do not include qualitative data sources in this paper. Given our objective to highlight publicly available data sources to study immigrant SRH, we chose to focus on quantitative data, which are often more readily accessible than data from qualitative studies. That being said, we acknowledge the need for qualitative and mixed-method studies to identify the range of SRH issues that affect immigrant communities. For example, qualitative research can help explore how individual motivations, interpersonal dynamics, and social context influence immigrant women’s decision-making and outcomes related to SRH—information that is critical to understand immigrants’ access to and use of SRH services. These data can also help shape quantitative research that is community-relevant.\nThis study also does not assess the specificity of the information collected on immigration status and SRH across surveys. For instance, while we highlight which surveys assessed fertility history, the specific measures that represent this domain in each survey may vary. Some surveys may exclude abortion or miscarriage from fertility history or change the number of fertility-related measures collected over time, but these details are not reported here. In an effort to hone the focus of this review, we do not address all measures of SRH or immigration such as reproductive cancer screening or acculturation. These data are available in some of the data sources we reviewed, such as CHIS and Add Health. We encourage future research to examine how acculturation, assimilation, and identity affect a range of SRH behaviors and outcomes.\nWe do not present specific linkages between data sources, although data from many of the sources we reviewed can be linked to other information such as contextual data. Typically, a study’s website or data user manuals will indicate the linkage capabilities of a data source. Incorporating additional information such as census or birth data in the study of individuallevel outcomes can help assess the impact of contextual factors such affordable housing or neighborhood-level poverty.\nJ Health Care Poor Underserved. Author manuscript; available in PMC 2019 August 13.\nA uthor M anuscript A uthor M anuscript\nA uthor M anuscript A uthor M anuscript\nFinally, we do not include measures related to undocumented status in this paper, given the minority of surveys that collect these data and limitations in the quality of these data. For multiple reasons, including safety and confidentiality, undocumented status is rarely asked of survey respondents. Especially in the current political climate, individuals may be particularly hesitant to reveal or accurately report their documentation status.53 Without these data, it is and will continue to be challenging to assess the health status of this population and meet their varied and changing needs. We encourage researchers to continue employing innovative methods to estimate undocumented status.54\nRecommendations.\nThis paper brings to bear areas for improvement in future study design, data collection, and analysis in order to advance our understanding of immigrant SRH. For example, research on immigrants and their generational- as well as ethnicity-specific subgroups is often limited due to small sample sizes. In response, we echo previous recommendations to employ oversampling techniques and pool waves of data, when appropriate, to power subgroup analyses sufficiently.5,6 We also encourage wider use of local-level data sources, in addition to national datasets, to study immigrant SRH. State- or county-level data may better address research questions on specific immigrant populations given geographic clustering of these groups. Increased and ongoing collection of longitudinal data could also assess changes in health behaviors and outcomes over immigrant generations and include data on recently emigrated families.\nThere is also a need for more comprehensive data on immigrants and their SRH. Future health surveys should consider collecting a minimum set of data on immigrant status, race and ethnicity, and SRH. For example, factors related to generational status such as year of arrival, length of stay, respondent and parent nativity, and ancestry may be useful to assess immigration context.12–18,55 Measures of language proficiency should also be collected more consistently and with increased specificity. Indeed, limited English proficiency can impede access to care and exacerbate other nonfinancial barriers.9 We also recommend collecting race, ethnicity, and country of origin data with as much specificity and granularity as possible given the heterogeneity of the immigrant population and of immigrants’ experiences.\nFurthermore, there is a distinct lack of data on SRH coverage, care, behaviors, and outcomes in the immigrant population; only two (NSFG and Add Health) of the national surveys reviewed in this paper collected information on each of these topics. Without these data, disparities in SRH service use and access may remain hidden within the immigrant population and between immigrants and non-immigrants. Instead, future research efforts on immigrant health, generally, and SRH, specifically, should make sure to collect data related to use of and access to health insurance status, contraceptive counseling and services, screening for reproductive cancers, STI prevention and treatment, gynecological and obstetric services, and abortion. These data are particularly important given mounting legal and logistical barriers to obtaining reproductive health care in the U.S., combined with enforcement of immigration policies, which may uniquely target and affect immigrants’ access to SRH care. Furthermore, data efforts that allow for the exploration of how\nJ Health Care Poor Underserved. Author manuscript; available in PMC 2019 August 13.\nA uthor M anuscript A uthor M anuscript\nA uthor M anuscript A uthor M anuscript\nindividual, interpersonal, community, and structural factors influence different immigrant women’s SRH experiences, decisions, and outcomes could also help inform policies and protocols that both enhance and safeguard immigrant women’s access to and use of SRH services as well as their wellbeing more broadly.\nIn general, there is a critical need for data sources to include measures of immigration and SRH. However, it is also important to note that data collection, on any topic, can be highly sensitive for immigrants in the United States. Fear of legal backlash in the current political environment may deter immigrants, regardless of documentation status, from disclosing personal information. Study participation may be further limited due to linguistic barriers or —specifically related to SRH research—the cultural stigma associated with topics such as sex, pregnancy, and abortion.56 In order to mitigate some of these concerns and increase the quality and quantity of immigrant SRH data, future research may consider adapting the language, tone of survey questions, and translation of instruments to meet the needs of specific immigrant groups more adequately, while also protecting their confidentiality. Involving and engaging immigrant populations throughout the research process—from formulating research questions and survey instruments to data collection, analysis, and dissemination—is also critical to developing relevant and culturally competent research. 7,57,58 These efforts can contribute to a better understanding of the sexual and reproductive health of immigrant groups, which, ultimately, will help inform programs and policies that aim to improve the overall health and wellbeing of the U.S. population.\nAcknowledgments\nSupport for this work was provided by the Guttmacher Center for Population Research Innovation and Dissemination (NIH grant 5 R24 HD074034). The authors thank Dr. Liza Fuentes, Dr. Laura D. Lindberg and Dr. Megan L. Kavanaugh for their insightful comments on earlier versions of the manuscript.\nReferences\n1. Pew Research Center. Modern immigration wave brings 59 million to U.S., driving population growth and change through 2065. Washington, DC: Pew Research Center, 2015 Available at: http:// www.pewhispanic.org/2015/09/28/modern-immigration-wave-brings-59-million-to-u-s-drivingpopulation-growth-and-change-through-2065/. 2. U.S. Census Bureau. 2016 American Community Survey 1-Year Estimates: Selected Characteristics of the Native and Foreign-born Populations, (Table S0501).Washington, DC: U.S. Census Bureau, 2016 Available at: https://factfinder.census.gov/faces/tableservices/jsf/pages/productview.xhtml? src=bkmk. 3. Grieco EM, Acosta YD, de la Cruz GP, et al. The foreign-born population in the United States: 2010. Washington, DC: U.S. Census Bureau, 2012 Available at: https://www.census.gov/library/ publications/2012/acs/acs-19.html. 4. Johnson PJ, Blewett LA, Davern M. Disparities in public use data availability for race, ethnic, and immigrant groups: national surveys for healthcare disparities research. Med Care. 2010 12;48(12): 1122–7. 10.1097/MLR.0b013e3181ef984e [PubMed: 20966785] 5. Islam NS, Khan S, Kwon S, et al. Methodological issues in the collection, analysis, and reporting of granular data in Asian American populations: historical challenges and potential solutions. J Health Care Poor Underserved. 2010 11;21(4):1354–81 [PubMed: 21099084] 6. Lau DT. Advancing the field of public health surveillance and survey methods. Am J Public Health. 2017 6;107(6):822 10.2105/AJPH.2017.303799 [PubMed: 28498766]\nJ Health Care Poor Underserved. Author manuscript; available in PMC 2019 August 13.\nA uthor M anuscript A uthor M anuscript\nA uthor M anuscript A uthor M anuscript\n7. Ro MJ, Yee AK. Out of the shadows: Asian Americans, Native Hawaiians, and Pacific Islanders. Am J Public Health. 2010 5;100(5):776–8. Epub 2010 Mar 18. 10.2105/AJPH.2010.192229 [PubMed: 20299635] 8. Waters MC, Pineau MG, eds. Health status and access to care In: National Academies of Sciences, Engineering, and Medicine. The Integration of immigrants into American society. Washington, DC: National Academies Press, 2015:377–411. 9. Derose KP, Bahney BW, Lurie N, et al. Review: immigrants and health care access, quality, and cost. Med Care Res Rev. 2009 8;66(4):355–408. Epub 2009 Jan 29. 10.1177/1077558708330425 [PubMed: 19179539] 10. Chin KK. Improving public health surveillance about Asian Americans, Native Hawaiians, and Pacific Islanders. Am J Public Health. 2017 6;107(6):827–8. 10.2105/AJPH.2017.303802 [PubMed: 28498752] 11. Gee GC, Ford CL. Structural racism and health inequities: old issues, new directions. Du Bois Rev. 2011 4;8(1):115–32. 10.1017/S1742058X11000130 [PubMed: 25632292] 12. Thamer M, Richard C, Casebeer AW, et al. Health insurance coverage among foreign-born US residents: the impact of race, ethnicity, and length of residence. Am J Public Health. 1997 1;87(1): 96–102. 10.2105/AJPH.87.1.96 [PubMed: 9065235] 13. Chawla N, Breen N, Liu B, et al. Asian American women in California: a pooled analysis of predictors for breast and cervical cancer screening. Am J Public Health. 2015 2;105(2):e98–109. 10.2105/AJPH.2014.302250 14. Carter M Fertility of Mexican immigrant women in the U.S.: a closer look. Soc Sci Q. 2000;81(4): 1073–86. 15. Clough J, Lee S, Chae DH. Barriers to health care among Asian immigrants in the United States: a traditional review. J Health Care Poor Underserved. 2013 2;24(1):384–403. 10.1353/hpu. 2013.0019 [PubMed: 23377740] 16. Chin JJ, Kang E, Kim JH, et al. Serving Asians and Pacific Islanders with HIV/AIDS: challenges and lessons learned. J Health Care Poor Underserved. 2006 11;17(4):910–27. 10.1353/hpu. 2006.0119 [PubMed: 17242538] 17. Kelaher M, Jessop DJ. Differences in low-birthweight among documented and undocumented foreign-born and US-born Latinas. Soc Sci Med. 2002 12;55(12):2171–5. 10.1016/ S0277-9536(01)00360-4 [PubMed: 12409130] 18. Korinek K, Smith KR. Prenatal care among immigrant and racial-ethnic minority women in a new immigrant destination: exploring the impact of immigrant legal status. Soc Sci Med. 2011 5;72(10):1695–703. Epub 2011 Apr 6. 10.1016/j.socscimed.2011.02.046 [PubMed: 21530038] 19. Goel MS, Wee CC, McCarthy EP, et al. Racial and ethnic disparities in cancer screening. J Gen Intern Med. 2003 12;18(12):1028–35. 10.1111/j.1525-1497.2003.20807.x [PubMed: 14687262] 20. Kagawa-Singer M, Pourat N, Breen N, et al. Breast and cervical cancer screening rates of subgroups of Asian American women in California. Med Care Res Rev. 2007 12;64(6):706–30. Epub 2007 Sep 5. 10.1177/1077558707304638 [PubMed: 17804823] 21. Tsui J, Saraiya M, Thompson T, et al. Cervical cancer screening among foreign-born women by birthplace and duration in the United States. J Womens Health (Larchmt). 2007 12;16(10):1447– 57. 10.1089/jwh.2006.0279 [PubMed: 18062760] 22. National Academies of Sciences, Engineering, and Medicine. The integration of immigrants into American society. Washington, DC: National Academies Press, 2015. 23. National Institute of Health (NIH). Racial and ethnic categories and definitions for NIH diversity programs and for other reporting purposes. Bethesda, MD: NIH, 2015 Available at: https:// grants.nih.gov/grants/guide/notice-files/NOT-OD-15-089.html. 24. Guttmacher Center for Population Research Innovation and Dissemination. 2009 National Survey of Reproductive and Contraceptive Knowledge (“The Fog Zone”) [questionnaire and codebook]. New York, NY: Guttmacher Institute, 2009 Available at: https://www.guttmacher.org/populationcenter/dataset/2009-national-survey-reproductive-and-contraceptive-knowledge. 25. Institute for Social Research, University of Michigan. Panel Study of Income Dynamics (PSID)— Child Development Supplement (CDS) [questionnaire and user guide]. Ann Arbor, MI: University of Michigan, 2008 Available at: https://psidonline.isr.umich.edu/Guide/documents.aspx.\nJ Health Care Poor Underserved. Author manuscript; available in PMC 2019 August 13.\nA uthor M anuscript A uthor M anuscript\nA uthor M anuscript A uthor M anuscript\n26. U.S. Bureau of Labor Statistics. National Longitudinal Survey of Youth—1997 (NLSY97) [questionnaire and NLS investigator]. Washington, DC: Bureau of Labor Statistics, 2013 Available at: https://www.nlsinfo.org/content/cohorts/nlsy97/other-documentation/questionnaires. 27. U.S. Bureau of Labor Statistics. National Longitudinal Survey of Youth—1979 (NLSY79) [questionnaire and NLS investigator]. Washington, DC: Bureau of Labor Statistics, 2012 Available at: https://www.nlsinfo.org/content/cohorts/nlsy79/other-documentation/questionnaires. 28. Princeton University’s Center for Research on Child Wellbeing (CRCW) and Center for Health and Wellbeing (CHW), Columbia Population Research Center (CPRC), Columbia University’s National Center for Children and Families (NCC). Fragile Families and Child Wellbeing Study (FFCWS) [questionnaire maps and guide to the public use files]. Princeton, NJ: Princeton University, 2010 Available at: https://fragilefamilies.princeton.edu/about. 29. Institute for Social Research, University of Michigan. Panel Study of Income Dynamics (PSID)— individual and family data (main) [questionnaire and codebook]. Ann Arbor, MI: University of Michigan, 2015 Available at: https://psidonline.isr.umich.edu/Guide/documents.aspx. 30. UNC Carolina Population Center. National longitudinal study of adolescent to adult health (Add Health) [codebook explorer]. Chapel Hill, NC: University of North Carolina, 2008 Available at: https://www.cpc.unc.edu/projects/addhealth/documentation/ace/tool/instruments. 31. Guttmacher Center for Population Research Innovation and Dissemination. 2008 Abortion Patient Survey (APS) [questionnaire and codebook]. New York, NY: Guttmacher Institute, 2008 Available at: https://www.guttmacher.org/population-center/dataset/2008-abortion-patient-survey-aps. 32. Centers for Disease Control and Prevention (CDC). National Survey of Family Growth (NSFG) [questionnaire and codebook]. Atlanta, GA: CDC, 2015 Available at: https://www.cdc.gov/nchs/ nsfg/index.htm. 33. University of Wisconsin Center for Demography. National Survey of Families and Households (NSFH) [content outline and codebook]. Madison, WI: University of Wisconsin, 2003 Available at: http://www.ssc.wisc.edu/nsfh/. 34. Centers for Disease Control and Prevention (CDC). National Health and Nutrition Examination Survey (NHANES) [questionnaires and response rates and population totals]. Atlanta, GA: CDC, 2014 Available at: https://wwwn.cdc.gov/nchs/nhanes/continuousnhanes/default.aspx? BeginYear=2013. 35. U.S. Census Bureau. Current Population Survey (CPS) [questionnaire and dataferrett]. Washington, DC: U.S. Census Bureau, 2016 Available at: https://www.census.gov/programs-surveys/cps/ technical-documentation/questionnaires.html. 36. Centers for Disease Control and Prevention (CDC). National Health Interview Survey (NHIS) [questionnaire and variable frequencies]. Atlanta, GA: CDC, 2015 Available at: https:// www.cdc.gov/nchs/nhis/nhis_questionnaires.htm. 37. U.S. Census Bureau. American Community Survey (ACS) [questionnaire and American FactFinder]. Washington, DC: U.S. Census Bureau, 2015 Available at: https://www.census.gov/ programs-surveys/acs/methodology/questionnaire-archive.2015.html. 38. Centers for Disease Control and Prevention (CDC). Pregnancy Risk Assessment Monitoring System (PRAMS) [questionnaire]. Atlanta, GA: CDC, 2016 Available at: https://www.cdc.gov/ prams/index.htm. 39. UCLA Center for Health Policy Research. California Health Interview Survey (CHIS) [questionnaire and sample sizes]. Los Angeles, CA: UCLA, 2015 Available at: http:// healthpolicy.ucla.edu/chis/design/Pages/overview.aspx. 40. California Department of Health Care Services. California Women’s Health Survey (CWHS) [questionnaire]. Sacramento, CA: California Department of Health Care Services, 2012 Available at: http://www.dhcs.ca.gov/dataandstats/Pages/CWHS.aspx. 41. California Department of Public Health. Maternal and Infant Health Assessment (MIHA) [questionnaire and methods]. Sacramento, CA: California Department of Public Health, 2018 Available at: https://www.cdph.ca.gov/Programs/CFH/DMCAH/MIHA/Pages/Questionnaire.aspx. 42. Los Angeles County Department of Public Health. Los Angeles County Health Survey (LACHS) [questionnaire and methodology report]. Los Angeles, CA: Los Angeles County Department of Public Health, 2011 Available at: http://publichealth.lacounty.gov/ha/hasurveyintro.htm.\nJ Health Care Poor Underserved. Author manuscript; available in PMC 2019 August 13.\nA uthor M anuscript A uthor M anuscript\nA uthor M anuscript A uthor M anuscript\n43. Potter JE, Hopkins K, Amastae J, et al. Border Contraceptive Access Study (BCAS) [questionnaire and codebook]. Ann Arbor, MI: University of Michigan, 2006 Available at: https:// www.icpsr.umich.edu/icpsrweb/DSDR/studies/32561/version/1/datadocumentation. 44. New York City Department of Health and Mental Hygiene. New York City Community Health Survey (NYCCHS) [methodology report]. New York, NY: New York City Department of Health and Mental Hygiene, 2014 Available at: https://a816-healthpsi.nyc.gov/epiquery/CHS/ CHSXIndex.html. 45. Centers for Disease Control and Prevention (CDC). National Vital Statistics System: birth data [standard form]. Atlanta, GA: CDC, 2015 Available at: https://www.cdc.gov/nchs/nvss/births.htm. 46. U.S. Bureau of Labor Statistics. National Longitudinal Survey of Youth 1979—Children and young adults (NLSY79 Child/YA) [questionnaire and NLS investigator]. Washington, DC: U.S. Bureau of Labor Statistics, 2012 Available at: https://www.nlsinfo.org/content/cohorts/nlsy79-children. 47. Institute for Social Research, University of Michigan. Panel Study of Income Dynamics (PSID)— child development supplement, 2014 (CDS-2014) [questionnaire and user guide]. Ann Arbor, MI: University of Michigan, 2014 Available at: https://psidonline.isr.umich.edu/Guide/documents.aspx. 48. Institute for Social Research, University of Michigan. Panel Study of Income Dynamics (PSID)— transition into adulthood supplement [questionnaire and codebook]. Ann Arbor, MI: University of Michigan, 2013 Available at: https://psidonline.isr.umich.edu/Guide/documents.aspx. 49. National Center for Education Statistics. Early Childhood Longitudinal Program (ECLS): birth cohort (ECLS-B) [questionnaire and descriptive tables]. Washington, DC: U.S. Department of Education, 2006 Available at: https://nces.ed.gov/ecls/birthinstruments.asp. 50. National Center for Education Statistics. Early Childhood Longitudinal Program (ECLS) — kindergarten class of 1998–99 (ECLS-K) [questionnaire and descriptive tables]. Washington, DC: U.S. Department of Education, 2007 Available at: https://nces.ed.gov/ecls/kinderinstruments.asp. 51. Princeton University, U.S. Immigration and Naturalization Service (INS). New Immigrant Survey (NIS) [questionnaire and codebook]. Princeton, NJ: Princeton University, 2009 Available at: https://nis.princeton.edu/documentation.html. 52. U.S. Census Bureau. Survey of Income and Program Participation [questionnaire]. Washington, DC: U.S. Census Bureau, 2008 Available at: https://www.census.gov/programs-surveys/sipp/techdocumentation/questionnaires/2008-questionnaires.html. 53. Massey DS. Challenges to surveying immigrants In: Tourangeau R, Edwards B, Johnson TP, et al., eds. Hard-to-survey populations. Cambridge, United Kingdom: Cambridge University Press, 2014:270–92. 10.1017/CBO9781139381635.017 54. Capps R, Fix M, van Hook J, et al. A demographic, socioeconomic and health coverage profile of unauthorized immigrants in the United States. Washington, DC: Migration Policy Institute, 2013. 55. Trinh-Shevrin C, Islam NS, Rey MJ, eds. Asian American communities and health: context, research, policy, and action (1st ed.). San Francisco, CA: Jossey-Bass, 2009. 56. Okazaki S Influences of culture on Asian Americans’ sexuality. J Sex Res. 2002 2;39(1):34–41. 10.1080/00224490209552117 [PubMed: 12476254] 57. Panapasa S, Jackson J, Caldwell C, et al. Community-based participatory research approach to evidence-based research: lessons from the Pacific Islander American Health Study. Prog Community Health Partnersh. 2012 Spring;6(1):53–8. 10.1353/cpr.2012.0013 [PubMed: 22643788] 58. Cook WK, Weir RC, Ro M, et al. Improving Asian American, Native Hawaiian, and Pacific Islander health: national organizations leading community research initiatives. Prog Community Health Partnersh. 2012 Spring;6(1):33–41. 10.1353/cpr.2012.0008 [PubMed: 22643786]\nJ Health Care Poor Underserved. Author manuscript; available in PMC 2019 August 13.\nA uthor M anuscript A uthor M anuscript\nA uthor M anuscript A uthor M anuscript\nA uthor M anuscript A uthor M anuscript\nA uthor M anuscript A uthor M anuscript\nTa b\nle 1\n.\nD E\nSC R\nIP T\nIO N\nS O\nF N\nA T\nIO N\nA L\n-L E\nV E\nL D\nA TA\nSE T\nS, U\nN IT\nE D\nS TA\nT E\nS, 1\n98 7–\n20 17\nSt ud\ny ai\nm s\nan d\nde si\ngn Sa\nm pl\ne si\nze Sa\nm pl\ne pa\npe r\nN am\ne of\ns tu dy A ge nc y Sh or t g en er al d\nes cr\nip tio\nn of\ns tu\ndy ’s\na im\ns. S\nur ve\ny de\nsi gn\n: c ro\nss -s\nec tio\nna l/c\noh or\nt/e tc\n, h ow\nsu\nrv ey\nis c\non du\nct ed\n/ty pe\no f\nda ta\n( po\npu la\ntio n-\nba se\nd/ ho\nus eh\nol d/\ncl in\nic -b\nas ed ) »I nt er va ls ( ra ng e of y ea rs a nd # o f w av es )\n» R\nep re\nse nt\nat iv\nen es s » O ve rs am pl ed g ro\nup s\n» To\nta l s\nam pl\ne si\nze (\nm os\nt r ec\nen t y\nea r)\n» N\num be\nr of\nr es\npo nd\nen ts\n/w om\nen a\nge 1\n5– 44\n( ye\nar )\n» N\num be\nr of\nf or\nei gn\nb or\nn (y\nea r)\nFu ll\nci ta\ntio n\n(e xa\nm pl\ne of\na n\nim m\nig ra\nnt\nhe al\nth /S\nR H\ns tu\ndy u\nsi ng\nth es\ne da\nta )\nA m\ner ic\nan C\nom m\nun ity\nS ur\nve y\n(A C S) U .S . C en su s B ur ea u A C S pr ov id es b ro ad s oc ia l, ec on om\nic , a\nnd h\nou si\nng p\nro fi\nle s\nat th\ne st\nat e\nan d\nco un\nty le\nve l.\nSu rv\ney d\nes ig\nn: c\nro ss\n-s ec\ntio na\nl h ou\nse ho\nld s\nur ve y » C on tin uo us d at a co lle ct io n w ith a nn ua l d at a re\nle as\ne\n» N\nat io\nna lly\nr ep\nre se\nnt at\niv e\n» 3,\n14 7,\n00 0\nto ta\nl ( 20\n15 )\n» 56\n3, 90\n0 w\nom en\n1 5–\n44 (\n20 15 ) » 81 ,7 00 f or ei gn b or n w om en 1\n5– 44\n( 20\n15 )\nSi ng\nh G\nK , R\nod ri\ngu ez\n-L ai\nnz A\n, K og\nan M\nD .\nIm m\nig ra\nnt h\nea lth\nin eq\nua lit\nie s\nin th\ne U\nni te d St at es : u se o f ei gh t m aj or n at io na l d at a sy st\nem s.\nT\nhe S\nci en\ntif ic\nW or\nld J\nou rn\nal . 2\n01 3;\n20 13\n:l– 21 . do i:1 0. 11 55 /2 01 3/ 51 23 13 .\nN at\nio na\nl L on\ngi tu\ndi na\nl S tu\ndy o\nf A\ndo le\nsc en\nt t o\nA du\nlt H\nea lth\n( A\ndd H\nea lth ) U N C C ar ol in a Po pu la tio n C en te r A dd H ea lth b eg an a s a st ud y on a do le sc en t h ea lth b ut h as s in ce e xp an de\nd to\ns tu\ndy in g de ve lo pm en ta l a nd h ea lth tr aj ec to ri es f ro m a do le sc en ce to a du lth oo d. Su rv ey d es ig n: lo ng itu di na l s tu dy o f a co ho rt o f ad ol es ce nt s w ho w er e in 7 th –1 2t h gr\nad e\nin\n19 94\n–9 5;\ns ch\noo l-\nba se\nd su\nrv ey\n» 19\n94 –2\n00 8\n(o ng\noi ng\n): 5\nw av\nes o\nf da\nta\n» N\nat io\nna lly\nr ep\nre se\nnt at\niv e\n» O\nve rs\nam pl\ne of\nA fr\nic an\n-A m\ner ic\nan a\ndo le\nsc en\nts\nw ith\na p\nar en\nt w ith\na C\nol le\nge d\neg re e » 15 ,7 00 to ta l ( 20 08 ) » 10 ,5 00 w om en 2 5– 34 ( 19 95 ) » 1, 90 0 fo re ig n bo rn ( 19 95 )\nH ah\nm H\nC , L\nah if\nf M\n, B ar\nre to\nR M\n. A si\nan\nA m\ner ic\nan a\ndo le\nsc en\nts ’\nfi rs\nt s ex\nua l i\nnt er\nco ur\nse :\nG en\nde r\nan d\nac cu\nltu ra\ntio n\ndi ff\ner en\nce s.\nPe\nrs pe\nct iv\nes o\nn se\nxu al\na nd\nr ep\nro du\nct iv\ne he\nal th . 20 06 ;3 8( l) :2 8– 36 .\nA bo\nrt io\nn Pa\ntie nt\nS ur\nve y\n(A PS ) G ut tm ac he r C en te r fo r Po pu la\ntio n\nR es\nea rc\nh In\nno va\ntio n\nan d\nD is\nse m\nin at\nio n\nA PS\nc ol\nle ct\ns da\nta f\nro m\nw om\nen a\nbo ut\nth ei\nr ab\nor tio\nn an\nd ot\nhe r\nse xu\nal a\nnd r\nep ro\ndu ct\niv e\nhe al\nth\nm ea\nsu re\ns. S\nur ve\ny de\nsi gn\n: c ro\nss -s\nec tio\nna l s\nur ve\ny of\nw om\nen o\nbt ai\nni ng\na bo\nrt io\nns , c\nlin ic\n-b as\ned\nsu rv ey » 19 87\n–2 01\n2 (o\nng oi\nng ):\n5 r\nou nd\ns bu\nt o nl\ny 20\n08 p\nub lic\nal ly\na va\nila bl\ne cu\nrr en\ntly\n» N\nat io\nna lly\nr ep\nre se\nnt at\niv e\nof h\nea lth\nf ac\nili tie s » 9, 50 0 to ta l w om en f ro m 9 5 fa ci lit ie s (2 00 8) » 9, 50 0 w om en 1 5– 44 ( 20 08 ) » 1, 50 0 fo re ig n bo rn w om en 1 5– 44 ( 20 08 )\nJe rm\nan J\n, J on\nes R\nK , O\nnd a\nT. C\nha ra\nct er\nis tic\ns of\nU\nS A\nbo rt\nio n\nPa tie\nnt s\nin 2\n01 4\nan d\nC ha\nng es\nsi\nnc e\n20 08\n. N ew\nY or\nk, N\nY : G\nut tm\nac he r In st itu te ; 2 01 6.\nC ur\nre nt\nP op\nul at\nio n\nSu rv\ney (\nC PS ) U .S . C en su s B ur ea u, U .S . B ur ea\nu of\nL ab\nor S\nta tis\ntic s\nC PS\nis th\ne pr\nim ar\ny so\nur ce\nf or\nm on\nth ly\nla bo\nr fo\nrc e\nst at\nis tic\ns bu\nt a ls\no co\nlle ct\ns da\nta s\nup pl\nem en\nta l\nin qu\nir ie\ns on\no th\ner to\npi cs\ns uc\nh as\nf er\ntil ity\na nd\nh ea\nlth in\nsu ra\nnc e.\nSu rv\ney d\nes ig\nn: 4\n-8 -4\ns am\npl e\nro ta\ntio n\nin w\nhi ch\na h\nou si\nng u\nni t o\nr gr\nou p\nqu ar\nte rs\nis in\nte rv\nie w\ned\nfo r\n4 co\nns ec\nut iv\ne m\non th\ns, r\nem ov\ned f\nro m\ns am\npl e\nfo r\n8 m\non th\ns, r\nein\nte rv\nie w\ned f\nor a\nno th\ner 4\nco\nns ec\nut iv\ne m\non th\ns, a\nnd th\nen r\net ir\ned f\nro m\ns am\npl e\npe rm\nan en\ntly , h\nou se\nho ld\ns ur\nve y\n» C\non tin\nuo us\nd at\na co\nlle ct\nio n;\nd at\na fo\nr su\npp le\nm en\nta l t\nop ic\ns m\nay b\ne co\nlle ct\ned a\nnn ua\nlly o r bi an nu al ly\n» N\nat io\nna lly\nr ep\nre se\nnt at\niv e\n» 18\n5, 50\n0 to\nta l (\n20 16 ) » 95 ,5 00 w om en ( 20\n16 )\n» 12\n,7 00\nf or\nei gn\nb or\nn w\nom en\n( 20\n16 )\nA lv\nir a-\nH am\nm on\nd M\n, G uz\nzo K\nB . F\ner til\nity\ndi ff\ner en\ntia ls\na cr\nos s\nra ce\n-e th\nni ci\nty a\nnd\nge ne\nra tio\nna l s\nta tu\ns: in\nco rp\nor at\nin g\nno n-\nhi sp\nan ic\nim\nm ig\nra nt\ns. P\nre se\nnt ed\na t:\nPo pu\nla tio n A ss oc ia tio n of A m er ic a 20 13 A nn ua\nl M ee\ntin g.\nA\ncc es\nse d\nJu ne\n2 , 2\n01 7.\nE ar\nly C\nhi ld\nho od\nL on\ngi tu\ndi na\nl S tu\ndy —\nB ir\nth c\noh or\nt ( E\nC L\nSB ) U .S . D ep ar tm en t o f E du ca tio n— N at io na l C en te r fo r E du ca tio n\nSt at\nis tic s E C L SB f ol lo w s ch ild re n’ s ea rl y co gn iti ve , s oc ia l, em ot io na l, an d ph ys\nic al\nd ev\nel op\nm en\nt f ro\nm\nbi rt\nh to\nk in\nde rg\nar te\nn en\ntr y.\nSu rv\ney d\nes ig\nn: lo\nng itu\ndi na\nl s tu\ndy o\nf a\nbi rt\nh co\nho rt\n( ch\nild re\nn bo\nrn in\n2 00\n1) ; p\nop ul\nat io\nnba\nse d\nsu rv ey » 20 01\n–2 00\n6: I\nni tia\nl i nt\ner vi\new a\nt 9 -m\non th\ns pl\nus 3\nw av\nes o\nf da\nta ; m\not he\nr ty\npi ca\nlly in\nte rv\nie w\ned\nat e\nve ry\nw av\ne; f\nat he\nr in\nte rv\nie w\ned a\nt i ni\ntia l a\nnd w\nav es\n1 a\nnd 2\n» N\nat io\nna lly\nr ep\nre se\nnt at\niv e\n» O\nve rs\nam pl\ne of\nC hi\nne se\na nd\no th\ner A\nsi an\na nd\nPa\nci fi\nc Is\nla nd\ner , A\nm er\nic an\nI nd\nia n\nan d\nA la\nsk a\nN at\niv e\nch ild\nre n,\ntw in\ns an\nd ch\nild re\nn bo\nrn w\nith lo\nw\nan d\nve ry\nlo w\nb ir\nth w\nei gh t » 1, 90 0 to ta l c hi ld re n (2 00\n6/ 20\n07 )\n» Su\nbgr\nou p\nsa m\npl e\nsi ze\ns no\nt r ea\ndi ly\na va\nila bl\ne\nG uz\nm an\nL , W\nild sm\nith E\n, M an\nlo ve\nJ , F\nra nz\net ta\nK\n. U ni\nnt en\nde d\nbi rt\nhs : p\nat te\nrn s\nby r\nac e\nan d\net hn\nic ity\na nd\nr el\nat io\nns hi\np ty\npe . P\ner sp\nec tiv\nes o n Se xu al a nd R ep ro du ct iv e H ea lth . 2 01 0; 42 (3 ): 17 6– 18 5. d oi :1 0. 13 63 /4 21 76 10 .\nE ar\nly C\nhi ld\nho od\nL on\ngi tu\ndi na\nl S tu\ndy —\nK in\nde rg\nar te\nn (E\nC L\nSK ) U .S . D ep ar tm en t o f E du ca tio n— N at io na l C en te r fo r E du ca tio n\nSt at\nis tic s E C L SK f ol lo w s ch ild re n’ s ex pe ri en ce w ith f am ily , s ch oo l, co m m un ity a\nnd in\ndi vi\ndu al\ng ro\nw th\nas\nit r\nel at\nes to\nth ei\nr sc\nho ol\np ro\ngr es\nsi on\na nd\np er\nfo rm\nan ce\n.\n» N\nat io\nna lly\nr ep\nre se\nnt at\niv e\n» 12\n,0 00\nto ta\nl ( 20\n07 )\n» Su\nbgr\nou p\nsa m\npl e\nsi ze\ns no\nt r ea\ndi ly\na va\nila bl\ne\nG uz\nm an\nL , W\nild sm\nith E\n, M an\nlo ve\nJ , F\nra nz\net ta\nK\n. U ni\nnt en\nde d\nbi rt\nhs : p\nat te\nrn s\nby r\nac e\nan d\net hn\nic ity\na nd\nr el\nat io\nns hi\np ty\npe . P\ner sp\nec tiv\nes o n Se xu al a nd R ep ro du ct iv e H ea lth . 2 01 0; 42 (3 ): 17 6– 18 5. d oi :1 0. 13 63 /4 21 76 10 .\nJ Health Care Poor Underserved. Author manuscript; available in PMC 2019 August 13.\nA uthor M anuscript A uthor M anuscript\nA uthor M anuscript A uthor M anuscript\nSt ud\ny ai\nm s\nan d\nde si\ngn Sa\nm pl\ne si\nze Sa\nm pl\ne pa\npe r\nSu rv\ney d\nes ig\nn: lo\nng itu\ndi na\nl c oh\nor t s\ntu dy\no f\nch ild\nre n\nw ho\ne nt\ner ed\nk in\nde rg\nar te\nn in\n1 99\n8– 19\n99\nun til\nth ey\ne nt\ner e\nig ht\nh gr\nad e,\np op\nul at\nio n\nba se d » 19 98 –2 00 7: 5 w av es o f da ta Fr ag ile F am ili es a nd C hi ld W el lb ei ng S tu dy\n( FF\nC W S) Pr in ce to n U ni ve rs ity ’s C en te r fo r R es ea rc h on C hi ld W\nel lin\ng an\nd C\nen te\nr fo\nr H\nea lth\na nd\nW\nel lb\nei ng\n; t he\nC ol\num bi\na Po\npu la\ntio n\nR es\nea rc\nh C\nen te\nr, an\nd C\nol um\nbi a\nU ni\nve rs\nity ’s\nN at\nio na l C en te r fo r C hi ld re n an d Fa m ili es FF C W S fo llo w s ch ild re n an d “f ra gi le f am ili es ,” w hi ch r ef er s to f am ily u ni ts o f un m ar ri ed pa re nt s an d th ei r ch ild re n, w ho a re a t g re at er r is k of b re ak in g up a nd li vi ng in p ov er ty th an m or e tr ad iti on al f am ili es . Su rv ey d es ig n: lo ng itu di na l s tu dy o f a co ho rt o f un m ar ri ed c ou pl es w ho se c hi ld re n w er e\nbo rn\nbe\ntw ee\nn 19\n98 a\nnd 2\n00 0;\np op\nul at\nio n-\nba se\nd su\nrv ey\n» 19\n98 –2\n01 7\n(o ng\noi ng\n): 6\nw av\nes o\nf da\nta\n» R\nep re\nse nt\nat iv\ne of\nn on\n-m ar\nita l b\nir th\ns in\ne ac\nh of\n2 0\nci tie\ns an\nd no\nnm\nar ita\nl b ir\nth s\nin U\nS ci\ntie s\nw ith\npo\npu la\ntio ns\no ve\nr 20\n0, 00 0 » 7, 10 0 to ta l ( 20 10 ) » 3, 20 0 w om en 2 3– 44 (\n20 10 ) » 80 0 fo re ig n bo rn w om en (\n20 10\n)\nTa yl\nor C\nA , G\nut er\nm an\nN B\n, L ee\nS J,\nR at\nho uz\nP J.\nIn\ntim at\ne pa\nrt ne\nr vi\nol en\nce , m\nat er\nna l s\ntr es\ns,\nna tiv\nity , a\nnd r\nis k\nfo r\nm at\ner na\nl m al\ntr ea\ntm en\nt o f\nyo un\ng ch\nild re\nn. A\nm J\nP ub\nlic H\nea lth . 20 09 ;9 9( 1) :1 75 –1 83 . d oi :1 0. 21 05\n/A JP\nH .\n20 07\n.1 26\n72 2.\nN at\nio na\nl H ea\nlth a\nnd N\nut ri\ntio n\nE xa\nm in\nat io\nn Su\nrv ey\n( N\nH A\nN E S) C en te r fo r D is ea se C on tr ol — N at io na l C en te r fo r H ea lth S ta tis\ntic s\nN H\nA N\nE S\nis a\np ro\ngr am\no f\nst ud\nie s\nde si\ngn ed\nto a\nss es\ns th\ne he\nal th\na nd\nn ut\nri tio\nna l s\nta tu\ns of\na du\nlts\nan d\nch ild\nre n\nin th\ne U S. Su rv ey d es ig n: c ro ss -s\nec tio\nna l,\nho us\neh ol\nd su\nrv ey\na nd\np hy\nsi ca\nl e xa\nm in\nat io ns » 19 71 –1 99 4: 3 r ou nd s of d at a at ir re gu la r in te rv al s; 1 99 9– 20 16 ( on go in g) : 9\nr ou\nnd s\nof d\nat a\nat\n2 ye\nar in\nte rv\nal s\nof c\non tin\nuo us\nd at\na co\nlle ct\nio n\n» N\nat io\nna lly\nr ep\nre se\nnt at\niv e\n» O\nve rs\nam pl\ne of\ng ro\nup s\nsu ch\na s\npe rs\non s\n60 a\nnd\nol de\nr, A\nfr ic\nan A\nm er\nic an\n, H is\npa ni\nc, a\nnd A\nsi an s (m ay d if fe r by s ur ve y ro un d) » 10 ,2 00 ( 20 14 ) » 5, 20 0 w om en ( 20 14 ) » 1, 90 0 fo re ig n bo rn ( 20 14 )\nSi ng\nh G\nK , R\nod ri\ngu ez\n-L ai\nnz A\n, K og\nan M\nD .\nIm m\nig ra\nnt h\nea lth\nin eq\nua lit\nie s\nin th\ne U\nni te d St at es : u se o f ei gh t m aj or n at io na l d at a sy st\nem s.\nT\nhe S\nci en\ntif ic\nW or\nld J\nou rn\nal . 2\n01 3;\n20 13\n:1 –2\n1.\ndo i:\n10 .1\n15 5/\n20 13\n/5 12\n31 3.\nN at\nio na\nl H ea\nlth I\nnt er\nvi ew\nS ur\nve y\n(N H\nIS )\nC en\nte r\nfo r\nD is\nea se\nC on\ntr ol\n— N\nat io\nna l C\nen te\nr fo\nr H\nea lth\nS ta\ntis tic s N H IS is th e pr in ci pa l s ou rc e of in fo rm at io n on th e am ou nt , d is tr ib\nut io\nn an\nd ef\nfe ct\ns of\nil ln\nes s\nan d\ndi sa\nbi lit\ny in\nth e\nU S\nan d\nth e\nse rv\nic es\nr en\nde re\nd fo\nr or\nb ec\nau se\no f\nsu ch\nc on\ndi tio\nns .\nSu rv\ney d\nes ig\nn: c\nro ss\n-s ec\ntio na\nl, ho\nus eh\nol d\nsu rv ey » 19 57 –2 01 6 (o ng oi ng ): c on tin uo us d at a co lle\nct io\nn, r\nev is\ned in\n1 99\n7 an\nd re\nvi se\nd ag\nai n\nin 2\n01 8\nSp ec\nia l p\nop ul\nat io\nn fo\ncu s\non N\nat iv\ne H\naw ai\nia n\nan d\nPa ci\nfi c\nIs la\nnd er\na va\nila bl\ne 20\n16 ; A\ndd iti\non al\nH\nis pa\nni c,\nA si\nan a\nnd N\nat iv\ne H\naw ai\nia n\nor P\nac if\nic I\nsl an\nde r\nan ce\nst ry\n/o ri\ngi n\nto b\ne ad\nde d\nin 2\n01 8\n» N\nat io\nna lly\nr ep\nre se\nnt at\niv e\n» O\nve rs\nam pl\ne of\np er\nso ns\na ge\nd 65\no r\nol de\nr w\nho a\nre\nB la\nck , H\nis pa\nni c,\no r\nA si an » 10 3, 80 0 pe rs on s (2 01 5) » 53 ,5 00 w om en ( 20 15 ) » 17 ,7 00 f or ei gn b or n (2\n01 5)\nSi ng\nh G\nK , R\nod ri\ngu ez\n-L ai\nnz A\n, K og\nan M\nD .\nIm m\nig ra\nnt h\nea lth\nin eq\nua lit\nie s\nin th\ne U\nni te d St at es : u se o f ei gh t m aj or n at io na l d at a sy st\nem s.\nT\nhe S\nci en\ntif ic\nW or\nld J\nou rn\nal . 2\n01 3;\n20 13\n:l– 21 . do i: 10 .1 15 5/ 20 13 /5 12 31 3.\nN ew\nI m\nm ig\nra nt\nS ur\nve y\n(N IS ) Pr in ce to n U ni ve rs ity ; U .S . I\nm m\nig ra\ntio n\nan d\nN at\nur al\niz at\nio n\nSe rv\nic e\nN IS\nis a\nm ul\ntico\nho rt\np ro\nsp ec\ntiv e-\nre tr\nos pe\nct iv\ne pa\nne l s\ntu dy\no f\nne w\nle ga\nl i m\nm ig\nra nt\ns in\nth e\nU .S . Su rv ey d es ig n: m ul tico ho rt p ro sp ec tiv ere tr os pe ct iv e pa ne l s tu dy , p op ul at io nba se d su rv ey » 19 96 : p ilo t s tu dy ( N IS -P ); 2 00 3– 20 04 : b as el in e su rv ey ( N IS -2 00 3– 1) ; 2 00 7– 20 09 : f ol lo w u p (N IS -2 00 3– 2)\n» N\nat io\nna lly\nr ep\nre se\nnt at\niv e\nsa m\npl e\nof a\ndu lt\nim m\nig ra\nnt s\n(+ 18\n) ad\nm itt\ned to\nle ga\nl p er\nm an\nen t\nre si\nde nc\ne; c\nhi ld\nim m\nig ra\nnt s\nde fi\nne d\nas c\nhi ld\nre n\nof\nU .S\n. c iti\nze ns\nb or\nn ab\nro ad\n( <\n18 )\nor a\ndo pt\ned o\nrp ha\nns\n(< 5) » 8,\n60 0\nad ul\nts , 8\n00 c\nhi ld\nre n\n(2 00 9) » 5, 90 0 re sp on de nt s 19 –4 4 (2 00 4) » 8, 60 0 fo re ig n bo rn ( 20 04 )\nA kr\nes h\nIR , F\nra nk\nR . H\nea lth\ns el\nec tio\nn am\non g\nne w\nim m\nig ra\nnt s.\nA m\nJ P\nub lic\nH ea\nlth .\n20 08\n;9 8(\n11 ):\n20 58\n–2 06\n4. d\noi :1\n0. 21\n05 /A\nJP H . 20 06 .1 00 97 4.\nN at\nio na\nl L on\ngi tu\ndi na\nl S ur\nve y\nof Y\nou th\n( N\nL SY\n79 )\nU ni\nte d\nSt at\nes D\nep ar\ntm en\nt o f\nL ab\nor —\nB ur\nea u\nof L\nab or\nS ta\ntis tic s N L SY 79 g at he rs in fo rm at io n in a n ev en t h is to ry f or m at , i nc lu di\nng w\nor k,\nm ar\nri ag\ne, f\ner til\nity ,\ned uc\nat io\nn, in\nco m\ne, h\nea lth\n, i ns\nur an\nce , s\nub st\nan ce\nu se\na nd\ns ex\nua l a\nct iv\nity .\nSu rv\ney d\nes ig\nn: lo\nng itu\ndi na\nl s tu\ndy o\nf a\nco ho\nrt o\nf 14\n–2 2\nye ar\no ld\ns in\n1 97\n9, p\nop ul\nat io\nnba\nse d\nsu rv ey » 19 79\n–2 01\n4: 2\n6 w\nav es\no f\nda ta\n» N\nat io\nna lly\nr ep\nre se\nnt at\niv e\n» O\nve rs\nam pl\ne of\nB la\nck , H\nis pa\nni c\nor L\nat in\noan d m ili ta ry p er so ns » 7, 30 0 to ta l ( 20 12 ) » 6, 30 0 w om en 1 7– 23 ( 19 79 ) » 90 0 fo re ig n bo rn 1 7– 23 ( 19 79 )\nD or\niu s\nC , G\nuz zo\nK B\n. T he\nlo ng\na rm\no f\nm at\ner na l m ul tip ar tn er ed f er til ity a nd a do le sc en t w el lbe in g. P re se nt ed b y: A m er ic an S oc io lo gi ca l 20 13 A nn ua l M ee tin g. A cc es se d Ju ne 2 , 2 01 7.\nN at\nio na\nl L on\ngi tu\ndi na\nl S ur\nve y\nof Y\nou th\n( N\nL SY\n79 C\nhi ld\n/Y A ) U ni te d St at es D ep ar tm en t o f L ab or — B ur ea u of L ab or S ta tis\ntic s\nN L\nSY 79\nC hi\nld /Y\nA e\nxp an\nds th\ne in\nfo rm\nat io\nn co\nlle ct\ned b\ny th\ne N\nL SY\n79 a\nbo ut\nc hi\nld re\nn of\nf em\nal e\nre sp\non de\nnt s.\nA ge\na pp\nro pr\nia te\ns oc\nia l,\nco gn\niti ve\na nd\nb eh\nav io\nr as\nse ss\nm en\nts a\nre g\niv en\na s\nch ild\nre n\nm at\nur e.\nC hi\nld re\nn ov\ner 1\n5 (y\nou ng\na du\nlts )\nar e\nin te\nrv ie\nw ed\ns im\nila r\nto th\nat o\nf th\ne N\nL SY\n79 .\nSu rv\ney d\nes ig\nn: lo\nng itu\ndi na\nl s tu\ndy o\nf co\nho rt\no f\nch ild\nre n\nbo rn\na ft\ner 1\n97 3\nto N\nL SY\n79 m\not he\nrs ,\npo pu\nla tio\nnba\nse d\nsu rv\ney\n» 50\n0 ch\nild re\nn un\nde r\n15 ; 5\n,8 00\ny ou\nng a\ndu lts\no ve r 15 ( 20 12 ) » 5, 60 0 w om en ( 19 86 ) » Su bgr ou p sa m pl e si ze s no t r ea di ly a va ila bl e\nD or\niu s\nC , G\nuz zo\nK B\n. T he\nlo ng\na rm\no f\nm at\ner na l m ul tip ar tn er ed f er til ity a nd a do le sc en t w el lbe in g. P re se nt ed b y: A m er ic an S oc io lo gi ca l 20 13 A nn ua l M ee tin g. A cc es se d Ju ne 2 , 2 01 7.\nJ Health Care Poor Underserved. Author manuscript; available in PMC 2019 August 13.\nA uthor M anuscript A uthor M anuscript\nA uthor M anuscript A uthor M anuscript\nSt ud\ny ai\nm s\nan d\nde si\ngn Sa\nm pl\ne si\nze Sa\nm pl\ne pa\npe r\n» 19\n86 –2\n01 2:\n1 4\nw av\nes b\nia nn\nua lly\nf or\nc hi\nld re\nn sa\nm pl\ne; 1\n99 4–\n20 12\n: 1 0\nw av\nes b\nia nn\nua lly\nf or\nyo\nun g\nad ul\nts s\nam pl e C on ne ct ed to m ot he\nr’ s\nda ta\nin N\nL SY\n79 (\nL e.\nim m\nig ra\ntio n)\nN at\nio na\nl L on\ngi tu\ndi na\nl S ur\nve y\nof Y\nou th\n( N\nL SY\n97 )\nU ni\nte d\nSt at\nes D\nep ar\ntm en\nt o f\nL ab\nor —\nB ur\nea u\nof L\nab or\nS ta\ntis tic s N L SY 97 is d es ig ne d to d oc um en t t he tr an si tio n fr om s ch oo l t o\nw or\nk an\nd fr\nom y\nou th\nto\nad ul\nth oo\nd in\ncl ud\nin g\npe rs\non al\ne xp\ner ie\nnc e\nsu ch\na s,\nr el\nat io\nns hi\nps a\nnd s\nex ua\nl a ct\niv ity . Su rv ey d es ig n: lo ng itu di na l s tu dy o f a co ho rt o f ad ol es ce nt s bo rn b et w ee n 19 80 to\n1 98\n4,\npo pu\nla tio\nnba\nse d\nsu rv ey » 19 97 –2 01 7 (o ng oi ng ):\n1 7\nw av\nes o\nf da\nta e\nve ry\ny ea\nr si\nnc e\n19 97\na nd\nn ow\nb ie\nnn ia\nlly\n» N\nat io\nna lly\nr ep\nre se\nnt at\niv e\n» O\nve rs\nam pl\ne of\nH is\npa ni\nc or\nL at\nin o\nan d\nB la\nck\nad ol\nes ce\nnt s\n» 7,\n10 0\nto ta\nl ( 20\n13 )\n» 7,\n10 0\nre sp\non de\nnt s\n28 –3\n4 (2\n01 3)\n/1 2–\n18 (\nba se\nlin e)\n» 40\n0 fo\nre ig\nn bo\nrn (\n20 13\n)\nB ro\nnt e-\nT in\nke w\nJ , M\noo re\nK A\n, C ap\nps R\nC , Z\naf f\nJ.\nT he\nin fl\nue nc\ne of\nf at\nhe r\nin vo\nlv em\nen t o\nn yo\nut h\nri sk\nb eh\nav io\nrs a\nm on\ng ad\nol es\nce nt\ns: a\nc om\npa ri\nso n\nof n\nat iv\nebo\nrn a\nnd im\nm ig\nra nt\nf am\nili es\n. S oc\nia l\nSc ie\nnc e\nR es\nea rc\nh. 2\n00 6;\n35 (1\n): 18\n1– 20\n9. d\noi :\n10 .1\n01 6/\nj.s sr\nes ea\nrc h.\n20 04\n.0 8.\n00 2.\nN at\nio na\nl S ur\nve y\nof F\nam ily\nG ro\nw th\n( N\nSF G ) N at io na l C en te r fo r H ea lth S ta tis tic s, C en te\nrs f\nor D\nis ea\nse C\non tr\nol a\nnd P\nre ve\nnt io n N SF G g at he rs in fo rm at io n on f am ily li fe , m ar ri ag e an d di vo rc e, p re gn an cy , i nf\ner til\nity , u\nse o f co nt ra ce pt io n, a nd m en ’s a nd w om en ’s h ea lth . Su rv ey d es ig n: c ro ss -s ec tio na l s tu dy o f m en ( 15 –4 9) a nd w om en ( 15 –4 4) , p op ul at io nba se d su rv ey » 19 73 –2 01 5: 9 w av es o f da ta ( on go in g)\n» N\nat io\nna lly\nr ep\nre se\nnt at\niv e\n» 10\n,2 00\nto ta\nl ( 20\n15 )\n» 1,\n00 0\nfo re\nig n\nbo rn\nw om\nen 1\n5– 44\n( 20\n15 )\nH ay\nfo rd\nS , G\nuz zo\nK . A\nge , r\nel at\nio ns\nhi p\nst at\nus ,\nan d\nth e\npl an\nni ng\ns ta\ntu s\nof b\nir th\ns. D\nem og\nra ph\nic\nR es\nea rc\nh. 2\n01 0;\n23 :3\n65 –3\n98 . d\noi :1\n0. 40\n54 /\nD em\nR es\n.2 01\n0. 23\n.1 3.\nN at\nio na\nl S ur\nve y\nof F\nam ili\nes a\nnd H\nou se\nho ld\ns (N\nSF H ) C en te r fo r D em og ra ph y, U ni ve rs ity o f W is co ns in C ol le ct s da ta f ro m b ot h pa re nt s an d ch ild re n on f am ily\nf or\nm at\nio n,\nm ar\nri ag\ne, c\noh ab\nita tio\nn,\nfe rt\nili ty\n, p ar\nen tin\ng re\nla tio\nns , k\nin c\non ta\nct , a\nnd e\nco no\nm ic\na nd\np sy\nch ol\nog ic\nal w\nel l-\nbe in\ng of\nth e\npo pu\nla tio\nn in\nth e\nU .S . Su rv ey d es ig n: lo ng\nitu di\nna l s\ntu dy\n, h ou\nse ho\nld s\nur ve y » 19 87 –2 00 3: 3 w av es\n» N\nat io\nna lly\nr ep\nre se\nnt at\niv e\n» O\nve rs\nam pl\ne of\nB la\nck s,\nP ue\nrt o\nR ic\nan s,\nM ex\nic an\nA\nm er\nic an\ns, s\nin gl\nepa\nre nt\nf am\nili es\n, f am\nili es\nw ith\nst\nep c\nhi ld\nre n,\nc o-\nha bi\ntin g\nco up\nle s,\na nd\nr ec\nen tly\nm\nar ri\ned p\ner so ns » 7, 30 0 to ta l (\n20 03 ) » 7, 80 0 re sp on de nt\ns 20\n–4 4\n(1 98 7) » 1, 00 0 fo re ig n bo rn ( liv ed in f or ei\ngn c\nou nt\nry r\nig ht\naf\nte r\nbi rt\nh) (\n19 87\n)\nTo rr\nes S\nto ne\nR , R\niv er\na FI\n, B er\nda hl\nT . P\nre di\nct or s of d ep re ss io n am on g no nH is pa ni c W hi te s, M ex ic an s an d Pu er to R ic an s: a lo ok a t r ac e/ et hn ic ity a s a re fl ec tio n of s oc ia l r el at io ns . R ac e an d So ci et y. 2 00 4; 7( 2) :7 9– 94 . d oi :1 0. 10 16 / j.r ac so c. 20 05 .0 5. 00 3.\nN at\nio na\nl S ur\nve y\nof R\nep ro\ndu ct\niv e\nan d\nC on\ntr ac\nep tiv\ne K\nno w\nle dg\ne (F\nog Z\non e)\nG ut\ntm ac\nhe r\nC en\nte r\nfo r\nPo pu\nla tio\nn R\nes ea\nrc h\nIn no\nva tio\nn an\nd D\nis se\nm in\nat io n Fo g Z on e fo cu se s on th e at tit ud es a nd b eh av io rs o f un m ar ri ed y ou ng a du\nlts r\neg ar\ndi ng\npr\neg na\nnc y\npl an\nni ng\n, c on\ntr ac\nep tio\nn, a\nnd r\nel at\ned is\nsu es\n, i nc\nlu di\nng s\nex ua\nl r el\nat io\nns hi\np an d pr eg na nc y ex pe ri en ce s. Su rv ey d es ig n: c ro ss -s ec tio na l s tu dy o f un m ar ri ed y ou ng a du lts 1 8– 29 in 2 00 9, p op ul\nat io nba se d su rv ey\n» N\nat io\nna lly\nr ep\nre se\nnt at\niv e\nsa m\npl e\nof u\nnm ar\nri ed\nyo\nun g\nad ul ts » 1, 80 0 to\nta l (\n20 09 ) » 90 0 w om en 1 8– 29\n( 20\n09 )\n» 20\n0 fo\nre ig\nn bo\nrn 1\n8– 29\n( 20\n09 )\nW ils\non E\nK . D\nif fe\nre nc\nes in\nc on\ntr ac\nep tiv\ne us e ac ro ss g en er at io ns o f m ig ra tio n am on g w om\nen\nof m\nex ic\nan o\nri gi\nn. M\nat er\nn C\nhi ld\nH ea\nlth J . 20 09 ;1 3( 5) :6 41 . d oi :1 0. 10 07 / S1 09 95 -0 08 -0 38 2- 9.\nPa ne\nl S tu\ndy o\nf In\nco m\ne D\nyn am\nic s\n(P SI\nD )—\nIn di\nvi du\nal a\nnd F\nam ily\nD at\na (M\nai n)\nU ni\nve rs\nity o\nf M\nic hi\nga n\nPS ID\nf oc\nus es\no n\nth e\ndy na\nm ic\na sp\nec ts\no f\nec on\nom ic\na nd\nd em\nog ra\nph ic\nb eh\nav io\nr, in\ncl ud\nin g a w id e ra ng e of s oc io lo gi ca l a nd p sy ch ol og ic al m ea su re s. Su rv ey d es ig n: lo ng itu di na l s ur ve y, h ou se ho ld s ur ve y » 19 68 –1 99 6: a nn ua l i nt er vi ew s; 1 99 7– 20 15 : b ie nn ia l i nt er vi ew s on go in g PS ID is c ur re nt ly w or ki ng to s cr ee n an d re cr ui t n ew im m ig ra nt f am ili es ( fa m ili es in w hi ch bo th p ar tn er s m ig ra te d to th e U .S . a ft er 1 99 7) to a dd to th e sa m pl e in 2 01 7.\n» N\nat io\nna lly\nr ep\nre se\nnt at\niv e;\na dd\niti on\nal s\nam pl\ne of\nim\nm ig\nra nt\nf am\nili es\na dd\ned in\n1 99 7 » 77 ,2 00 to ta l ( al l y ea rs ) » 80 0 fo re ig n bo rn ( 19 97 ) » Fu rt he r su bgr ou p sa m pl e si ze\ns no\nt r ea\ndi ly\nav\nai la\nbl e\n(D is\nse rt\nat io\nn) K\nag ot\nho J\n. E xa\nm in\nin g\nT he\nL\non gi\ntu di\nna l I\nm pa\nct O\nf A\nss et\ns A\nnd I\nnc om\ne O n Im m ig ra nt H ea lth B eh av io rs . J an ua ry 2 00 9.\nPa ne\nl S tu\ndy o\nf In\nco m\ne D\nyn am\nic s\n(P SI\nD )—\nC hi\nld D\nev el\nop m\nen t S\nur ve\ny (C\nD S)\nU ni\nve rs\nity o\nf M\nic hi\nga n\nC D\nS su\nrv ey\ns ar\ne su\npp le\nm en\nts a\ndd ed\nto th\ne m\nai n\nPS ID\ns ur\nve y,\nc ol\nle ct\nin g\nda ta\na bo\nut c\nhi ld\nre n’ s he al th , d ev el op m en t a nd w el lbe in g w ith in th e co nt ex t o f fa m ili es , s ch oo l a nd n ei gh bo rh oo ds . Su rv ey d es ig n: lo ng itu di na l s ur ve y of a c oh or t s tu dy o f ch ild re n 0– 12 y ea rs o ld o f PS ID fa m ili es in 1 99 7, h ou se ho ld s ur ve y » 19 97 –2 00 8: 3 w av es o f da ta , C D SI (1 99 7) , C D SII ( 20 02 –2 00 3) , C D SII I (2 00 7– 20 08 )\n» N\nat io\nna lly\nr ep\nre se\nnt at\niv e\n» 1,\n50 0\nto ta\nl c hi\nld re\nn 5–\n19 (\n20 08 ) » 30 0 ch ild re n fr om n ew im m ig ra\nnt s\nam pl\ne; 9 0 fo re ig n bo rn c hi ld re n (1 99 7) » Fu rt he r su bgr ou p sa m pl e si ze s no t r ea di ly av ai la bl e\nPa ne\nl S tu\ndy o\nf In\nco m\ne D\nyn am\nic s\n(P SI\nD )—\nC hi\nld D\nev el\nop m\nen t S\nur ve\ny 20\n14 (\nC D\nS20\n14 )\nU ni\nve rs\nity o\nf M\nic hi\nga n\n» N\nat io\nna lly\nr ep\nre se\nnt at\niv e\n» 4,\n30 0\nto ta\nl c hi\nld re\nn 3–\n19 (\n20 14\n)\nJ Health Care Poor Underserved. Author manuscript; available in PMC 2019 August 13.\nA uthor M anuscript A uthor M anuscript\nA uthor M anuscript A uthor M anuscript\nSt ud\ny ai\nm s\nan d\nde si\ngn Sa\nm pl\ne si\nze Sa\nm pl\ne pa\npe r\nC D\nS su\nrv ey\ns ar\ne su\npp le\nm en\nts a\ndd ed\nto th\ne m\nai n\nPS ID\ns ur\nve y,\nc ol\nle ct\nin g\nda ta\na bo\nut c\nhi ld\nre n’ s he al th , d ev el op m en t a nd w el lbe in g w ith in th e co nt ex t o f fa m ili es , s ch oo l a nd n ei gh bo rh oo ds . Su rv ey d es ig n: lo ng itu di na l s ur ve y of a c oh or t s tu dy o f al l c hi ld re n 0– 17 y ea rs o ld o f PS ID fa m ili es in 2 01 4, h ou se ho ld s ur ve y » 20 14 –2 01 7: 1 w av e of d at a (o ng oi ng ) PS ID is c ur re nt ly w or ki ng to s cr ee n an d re cr ui t n ew im m ig ra nt f am ili es ( fa m ili es in w hi ch bo th p ar tn er s m ig ra te d to th e U .S . a ft er 1 99 7) to a dd to th e sa m pl e in 2 01 7. C hi ld re n fr om th es e fa m ili es w ill b e ad de d to f ut ur e C D S w av es .\n» N\nat iv\nity m\nay b\ne co\nde d\nfr om\nm ot\nhe r’ s im m ig ra tio n da ta ( ch ild ’s b ir th y ea r, m\not he\nr’ s\nna tiv\nity a\nnd c\niti ze\nns hi\np st\nat us\n, m ot\nhe r’\ns fi\nrs t s\nta y/\nliv ed\nin U\n.S .)\n» Fu\nrt he\nr su\nbgr\nou p\nsa m\npl e\nsi ze\ns no\nt r ea\ndi ly\nav\nai la\nbl e\nPa ne\nl S tu\ndy o\nf In\nco m\ne D\nyn am\nic s\n(P SI\nD )—\nT ra\nns iti\non to\nA du\nlth oo\nd Su\npp le\nm en\nt ( TA S) U ni ve rs ity o f M ic hi ga n TA S is a s up pl em en t a nd f ol lo w u p to th e or ig in al P SI D ’s C D S w hi ch e nd ed a t a ge 1\n8 an\nd it\nfi lls\nin th\ne ga\np in\nin fo\nrm at\nio n\nab ou\nt e ar\nly a\ndu lth\noo d\ntr an\nsi tio\nns b\nef or\ne th\ney e\nnt er\nth e\nPS ID\nm\nai n\nsa m\npl e\nSu rv\ney d\nes ig\nn: lo\nng itu\ndi na\nl s tu\ndy o\nf a\nco ho\nrt o\nf yo\nun g\nad ul\nts 1\n8– 28\nin 2\n00 5\nw ho\nh ad\npa\nrt ic\nip at\ned in\na t l\nea st\no ne\nC D\nS su\nrv ey\nr ou\nnd a\nnd f\nam ily\np ar\ntic ip\nat ed\nin c\nor e\nPS ID\n, h ou\nse ho\nld\nsu rv\ney ; f\nro m\n2 01\n7 fo\nrw ar\nd, T\nA S\nw ill\nin cl\nud in\ng al\nl y ou\nng a\ndu lts\nin P\nSI D\n» 20\n05 –2\n01 5:\n6 w\nav es\no f\nda ta\nb ie\nnn ia\nlly\n» N\nat io\nna lly\nr ep\nre se\nnt at\niv e\n» 1,\n80 0\nto ta\nl ( 20\n13 )\n» N\nat iv\nity m\nay b\ne co\nde d\nfr om\nm ot\nhe r’ s im m ig ra tio n da ta ( re sp on de nt ’s b ir th y\nea r,\nm ot\nhe r’ s na tiv ity a nd c iti ze ns hi p st at us , m ot he r’ s fi rs t s ta y/ liv ed in U .S .) » Fu rt he r su bgr ou p sa m pl e si ze s no t r ea di ly av ai la bl e\nSu rv\ney o\nf In\nco m\ne an\nd Pr\nog ra\nm P\nar tic\nip at\nio n\n(S IP P) U .S . C en su s B ur ea u » SI PP c ol le ct s da ta r el at ed to in co m e, la bo r fo rc e,\ns oc\nia l p\nro gr\nam p\nar tic\nip at\nio n\nan d\nde m\nog ra\nph ic\nc ha\nra ct\ner is\ntic s\nto m\nea su\nre th\ne ef\nfe ct\niv en\nes s\nof e\nxi st\nin g\nfe de\nra l,\nst at\ne an\nd lo\nca l\npr og\nra m s » Su rv\ney d\nes ig\nn: c\non tin\nuo us\ns er\nie s\nof n\nat io\nna l p\nan el\ns of\np er\nso ns\no ve\nr 15\n, h ou\nse ho\nld s\nur ve y » 19 84 –1 99 3: m ul tip le w av es f or 1 0 pa ne ls , r an gi ng o ve r 2– 4 ye ar s pe r pa ne l; 19 96 –2 01 4: m ul tip le w av es f or 5 p an el s\n» N\nat io\nna lly\nr ep\nre se\nnt at\niv e\n» 39\n,0 00\nto ta\nl ( 20\n08 )\n» Fu\nrt he\nr su\nbgr\nou p\nsa m\npl e\nsi ze\ns no\nt r ea\ndi ly\nav\nai la\nbl e\nC ap\nps R\n, B ac\nhm ei\ner J\nD , F\nix M\n, V an\nH oo\nk J.\nA\nD em\nog ra\nph ic\n, S oc\nio ec\non om\nic a\nnd H\nea lth\nC\nov er\nag e\nPr of\nile o\nf U\nna ut\nho ri\nze d\nIm m\nig ra\nnt s\nin\nth e\nU ni\nte d\nSt at\nes . W\nas hi\nng to\nn, D\nC : M\nig ra\ntio n\nPo lic\ny In\nst itu\nte ; 2\n01 3.\nN at\nio na\nl V ita\nl S ta\ntis tic\ns Sy\nst em\n: B ir\nth D\nat a\n(N V\nS— B\nir th\nD at\na) C\nen te\nrs f\nor D\nis ea\nse C\non tr\nol\nan d\nPr ev\nen tio n D at a sh ar in g\nin p\nub lic\nh ea\nlth f\nor r\neg is\ntr at\nio n\nof v\nita l e\nve nt\ns in\ncl ud\nin g\nbi rt\nhs , d\nea th\ns, m\nar ri\nag es , di vo rc es a nd f et al d ea th s. U .S . L aw r eq ui re s al l b ir th c er tif ic at es f or a ll bi rt hs w ith a ll st at es re po rt in g us in g un if or m r eg is tr at io n\n» 3,\n97 8,\n50 0\nbi rt\nhs (\n20 15 ) » Fu rt he r su bgr ou p sa\nm pl\ne si\nze s\nno t r\nea di\nly\nav ai\nla bl\ne\nSi ng\nh G\nK , R\nod ri\ngu ez\n-L ai\nnz A\n, K og\nan M\nD .\nIm m\nig ra\nnt h\nea lth\nin eq\nua lit\nie s\nin th\ne U\nni te d St at es : u se o f ei gh t m aj or n at io na l d at a sy st\nem s.\nT\nhe S\nci en\ntif ic\nW or\nld J\nou rn\nal . 2\n01 3;\n20 13 :l– 21 .d oi :1 0. 11 55 /2 01 3/ 51 23 13 .\nJ Health Care Poor Underserved. Author manuscript; available in PMC 2019 August 13.\nA uthor M anuscript A uthor M anuscript\nA uthor M anuscript A uthor M anuscript\nTa b\nle 2\n.\nD E\nSC R\nIP T\nIO N\nS O\nF ST\nA T\nE -\nA N\nD C\nO U\nN T\nY -L\nE V\nE L\nD A\nTA SE\nT S,\nU N\nIT E\nD S\nTA T\nE S,\n1 98\n7– 20\n17\nSt ud\ny ai\nm s\nan d\nde si\ngn Sa\nm pl\ne si\nze Sa\nm pl\ne pa\npe r\nN am\ne of\ns tu dy A ge nc y Sh or t g en er al d\nes cr\nip tio\nn of\ns tu\ndy ’s\na im s Su rv ey d es ig n: c ro ss -s ec tio na l/c oh or t/e tc\n, h ow\ns ur\nve y\nis c\non du\nct ed\n/ty pe\no f\nda ta\n(p\nop ul\nat io\nnba\nse d/\nho us\neh ol\nd/ cl\nin ic\n-b as\ned )\n» In\nte rv\nal s\n(r an\nge o\nf ye\nar s\nan d\n# of\nw av\nes )\n» R\nep re\nse nt\nat iv\nen es s » O ve rs am pl ed g ro\nup s\n» To\nta l s\nam pl\ne si\nze (\nm os\nt r ec\nen t y\nea r)\n» N\num be\nr of\nr es\npo nd\nen ts\n/w om\nen a\nge 1\n5– 44\n( ye\nar )\n» N\num be\nr of\nf or\nei gn\nb or\nn (y\nea r)\nFu ll\nci ta\ntio n\n(e xa\nm pl\ne of\na n\nim m\nig ra\nnt h\nea lth\n/S R\nH\nst ud\ny us\nin g\nth es\ne da\nta )\nB or\nde r\nC on\ntr ac\nep tiv\ne A\ncc es\ns St\nud y\n(B C\nA S)\nU ni\nve rs\nity o\nf Te\nxa s\nat A\nus tin\n— Po\npu la\ntio n\nR es\nea rc\nh C\nen te r B C A S co m pa re d th e ex pe ri en ce s of w om en w ho o bt ai ne d th\nei r\nco nt\nra ce\npt iv e pi lls in c lin ic s in E l P as o, T X to th os e fr om o ve r th e co un te r ph ar m ac ie s in C iu da d Ju ár ez . Su rv ey d es ig n: lo ng itu di na l » 20 06 –2 00 8: 4 w av es o f da ta\n» N\not r\nep re\nse nt\nat iv e » 1, 00 0 to ta l w om en\n( 20\n06 )\n» 1,\n00 0\nw om\nen 1\n8– 44\n( 20\n06 )\n» 70\n0 fo\nre ig\nn bo\nrn w\nom en\n( 20\n06 )\nA ik\nen A\nR A\n, P ot\nte r\nJE . A\nre L\nat in\na w\nom en\na m\nbi va\nle nt\nab\nou t p\nre gn\nan ci\nes th\ney a\nre tr\nyi ng\nto p\nre ve\nnt ?\nE vi\nde nc e fr om th e bo rd er c on tr ac ep tiv e ac ce ss s tu dy . P er sp ec t Se x R ep ro H . 2 01 3; 45 (4 ): 19 6– 20 3. d oi : 10 .1 36 3/ 45 19 61 3.\nC al\nif or\nni a\nH ea\nlth I\nnt er\nvi ew\nS ur\nve y\n(C H\nIS )\nU C\nL A\nC en\nte r\nfo r\nH ea\nlth P\nol ic\ny R\nes ea\nrc h\nC H\nIS is\nth e\nna tio\nn’ s\nla rg\nes t s\nta te\nh ea\nlth s\nur ve\ny, p\nro vi\ndi ng\nin fo\nrm at\nio n\non a\ndu lts , te en s, a nd c hi ld re n at th e st at e, c ou nt y, z ip c od e, a nd d is tr ic t l ev el s. Su rv ey d es ig n: c ro ss -s ec tio na l h ou se ho ld s ur ve y » 20 01 –2 01 5 (o ng oi ng ): b ia nn ua lly u nt il 20 13 w he n co nt in uo us d at a co lle ct io n be gi ns\n» R\nep re\nse nt\nat iv\ne of\nth e\nC al\nif or\nni a\npo pu\nla tio n » R ec en t o ve rs am pl es o f Ja pa ne se , K or ea n, a\nnd\nV ie\ntn am\nes e\npo pu\nla tio ns » 21 ,0 00 a du lts , 8 00\nte en\ns an\nd 2,\n20 0\nch ild\nre n\n(2 01 5) » 11 ,7 00 w om en ( 20 14 ) » 3, 90 0 re sp on de nt s 18 –4 4 (2 01 4) » 4, 60 0 fo re ig n bo rn ( 20 14 )\nB al\ndw in\nS B\n, S ol\nor io\nR , W\nas hi\nng to\nn D\nL , Y\nu H\n, H ua\nng\nY -C\n, B ro\nw n\nE R\n. W ho\nis u\nsi ng\ne m\ner ge\nnc y\nco nt\nra ce\npt io\nn? : A\nw ar\nen es\ns an\nd us\ne of\ne m\ner ge\nnc y\nco nt\nra ce\npt io\nn am\non g\nC al\nif or\nni a\nw om\nen a\nnd te\nen s.\nW\nom en\n’s H\nea lth\nI ss\nue s.\n2 00\n8; 18\n(5 ):\n36 0–\n36 8.\ndo i:\n10 .1\n01 6/\nj.w hi\n.2 00\n8. 06\n.0 05\n.\nC al\nif or\nni a\nW om\nen ’s\nH ea\nlth S\nur ve\ny (C\nW H S) C A D ep ar tm en t o f H ea lth C ar e Se rv ic es C W H S co lle ct s in fo rm at io n on a w id e va ri et\ny of\nh ea\nlth in\ndi ca\nto rs\na nd\nh ea\nlth -\nre la\nte d\nkn ow\nle dg\ne, b\neh av\nio rs\n, a nd\na tti\ntu de\ns of\nw om\nen in\nC al\nif or\nni a.\nSu rv\ney d\nes ig\nn: c\nro ss\n-s ec\ntio na\nl h ou\nse ho\nld s\nur ve y » 19 97 –2 01 2 (o ng oi ng ): 1 6 w av es o f da ta , a nn ua\nl\n» R\nep re\nse nt\nat iv\ne of\np op\nul at\nio n\nof w\nom en\n1 8\nan d\nol de\nr in\nC\nal if\nor ni a » 4, 00 0 w\nom en\n( 20\n12 )\n» 30\n,2 00\nr es\npo nd\nen ts\n1 8–\n44 (\nal l y\nea rs ) » Fu rt he r su bgr ou p sa m pl e si ze s no t r\nea di\nly a\nva ila\nbl e\nFo st\ner D\nG , B\nle y\nJ, M\nik an\nda J\n, e t a\nl. C\non tr\nac ep\ntiv e\nus e\nan d\nri sk\no f\nun in\nte nd\ned p\nre gn\nan cy\nin C\nal if\nor ni\na.\nC on\ntr ac\nep tio\nn. 2\n00 4;\n70 (l\n): 31\n–3 9.\nd oi\n:1 0.\n10 16 / j.c on tr ac ep tio n. 20 04 .0 1. 01 2.\nL A\nC ou\nnt y\nH ea\nlth S\nur ve\ny (L\nA C\nH S)\nL os\nA ng\nel es\nC ou\nnt y\nD ep\nar tm\nen t o\nf Pu\nbl ic\nH ea lth Pr im ar y so ur ce o f in fo rm at io n on a cc es s to h ea\nlth c\nar e,\nh ea\nlth c\nar e\nut ili\nza tio\nn,\nhe al\nth b\neh av\nio rs\n, h ea\nlth s\nta tu\ns, a\nnd k\nno w\nle dg\ne an\nd pe\nrc ep\ntio ns\no f\nhe al\nth -r\nel at\ned\nis su\nes a\nm on\ng th\ne L\nA C\nou nt\ny po\npu la\ntio n.\nSu rv\ney d\nes ig\nn: c\nro ss\n-s ec\ntio na\nl h ou\nse ho\nld s\nur ve y » 19 97 –2 01 5 (o ng oi ng ): 6 w av es o f da ta\n» R\nep re\nse nt\nat iv\ne of\na du\nlts a\nnd c\nhi ld\nre n\nre si\ndi ng\nin th e co un ty ’s e ig ht s er vi ce p la nn in g ar ea s an d 26 h ea lth di st ri ct s » O ve rs am pl e of c er ta in g eo gr ap hi c ar ea s in th e co un ty » 8, 00 0 ad ul ts a nd 6 ,0 00 p ar en ts /g ua rd ia ns o r pr im ar y ca re ta ke rs o f ch ild re n ag es 1 7 ye ar s or u nd er ( 20 11 ) » Su bgr ou p sa m pl e si ze s no t r ea di ly a va ila bl e\nY i S\nS, R\nob er\nts C\n, L ig\nht st\non e\nA S,\nS hi\nh M\n, T ri\nnh -\nSh ev\nri n\nC . D\nis pa\nri tie\ns in\nm ee\ntin g\nph ys\nic al\na ct\niv ity\ngu\nid el\nin es\nf or\nA si\nan A\nm er\nic an\ns in\ntw o\nm et\nro po\nlit an\nar\nea s\nin th\ne U\nni te\nd St\nat es\n. A nn\nE pi\nde m\nio l.\n20 15\n;2 5(\n9) :\n65 6–\n66 0.\ne2 .d\noi :1\n0. 10\n16 /j.\nan ne\npi de\nm .2\n01 5.\n05 .0\n02 .\nC al\nif or\nni a\nM at\ner na\nl I nf\nan t H\nea lth\nA ss\nes sm\nen t (\nM IH\nA )\nC al\nif or\nni a\nD ep\nar tm\nen t o\nf Pu\nbl ic\nH ea lth M IH A s ur ve ys w om en w ith r ec en t l iv\ne bi\nrt hs\nin C\nal if\nor ni\na, c\nol le\nct in\ng se\nlf -\nre po\nrt ed\nin fo\nrm at\nio n\nab ou\nt m at\ner na\nl a nd\nin fa\nnt e\nxp er\nie nc\nes a\nnd m\nat er\nna l\nat tit\nud es\na nd\nb eh\nav io\nrs b\nef or\ne, d\nur in\ng, a\nnd s\nho rt\nly a\nft er\np re\ngn an\ncy .\nSu rv\ney d\nes ig\nn: c\nro ss\n-s ec\ntio na\nl p op\nul at\nio n-\nba se\nd su\nrv ey\n» 20\n00 –2\n01 4\n(o ng\noi ng\n): a\nnn ua\nl d at\na co\nlle ct\nio n\n» R\nep re\nse nt\nat iv\ne of\na ll\nw om\nen 1\n5 ye\nar s\nan d\nol de\nr w\nho\nha ve\nh ad\na li\nve b\nir th\nin C\nal if\nor ni a » 7, 00 0 to ta l ( 20 14 ) » Su bgr ou p sa m pl e si ze s no t r\nea di\nly a\nva ila\nbl e\nC ub\nbi n\nC , B\nra ve\nm an\nP A\n, M ar\nch i K\nS, C\nha ve\nz G\nF,\nSa nt\nel li\nJS , G\nilb er\nt B JC\n. S oc\nio ec\non om\nic a\nnd r\nac ia l/ et hn ic d is pa ri tie s in u ni nt en de d pr eg na nc y am on g po st pa rt um w om en in C al if or ni a. M at er n C hi ld H\nea lth\nJ.\n2 00\n2; 6(\n4) :2\n37 –2\n46 . d\noi :1\n0. 10\n23 /A\n:1 02\n11 58\n01 62\n68 .\nN ew\nY or\nk C\nity C\nom m\nun ity\nH ea\nlth S\nur ve\ny (N\nY C\nC H S) N ew Y or k C ity D ep ar tm en t o f H ea lth a nd M en ta l H yg ie ne C H S pr ov id es d at a on th e he al th o f N ew Y or ke rs , i nc lu di ng\nn ei\ngh bo\nrh oo\nd,\nbo ro\nug h,\na nd\nc ity\nw id\ne es\ntim at\nes o\nn a\nbr oa\nd ra\nng e\nof c\nhr on\nic d\nis ea\nse s\nan d\nbe ha\nvi or\nal r\nis k\nfa ct\nor s.\n» R\nep re\nse nt\nat iv\ne of\na du\nlts 1\n8– 64\na nd\nth ei\nr ch\nild re\nn fr\nom\nal l f\niv e\nbo ro\nug hs\no f\nN ew\nY or\nk C ity » 9, 00 0 to ta l ( an nu al s am pl e) » 3, 40 0 re sp on de nt s 18 –4 4 (2 01 4) » 4, 90 0 w om en ( 20 14 )\nY i S\nS, R\nob er\nts C\n, L ig\nht st\non e\nA S,\nS hi\nh M\n, T ri\nnh -\nSh ev\nri n\nC . D\nis pa\nri tie\ns in\nm ee\ntin g\nph ys\nic al\na ct\niv ity\ngu\nid el\nin es\nf or\nA si\nan A\nm er\nic an\ns in\ntw o\nm et\nro po\nlit an\nar\nea s\nin th\ne U\nni te\nd St\nat es\n. A nn\nE pi\nde m\nio l.\n20 15\n;2 5(\n9) :\n65 6–\n66 0.\ne2 . d\noi :1\n0. 10\n16 /j.\nan ne\npi de\nm .2\n01 5.\n05 .0\n02 .\nJ Health Care Poor Underserved. Author manuscript; available in PMC 2019 August 13.\nA uthor M anuscript A uthor M anuscript\nA uthor M anuscript A uthor M anuscript\nSt ud\ny ai\nm s\nan d\nde si\ngn Sa\nm pl\ne si\nze Sa\nm pl\ne pa\npe r\nSu rv\ney d\nes ig\nn: c\nro ss\n-s ec\ntio na\nl p op\nul at\nio n-\nba se\nd su\nrv ey\n» 20\n02 –2\n01 4\n(o ng\noi ng\n): a\nnn ua\nl d at\na co\nlle ct\nio n\n» 3,\n90 0\nfo re\nig n\nbo rn\n( 20\n14 )\nPr eg\nna nc\ny R\nis k\nA ss\nes sm\nen t M\non ito\nri ng\nS ys\nte m\n( PR\nA M S) C en te r fo r D is ea se C on tr ol a nd P re ve nt io n PR A M S is a s ur ve ill an ce p ro je ct th ro ug h th e C D C a nd h ea\nlth d\nep ar\ntm en\nts in\n4 7\npa rt\nic ip\nat in\ng st\nat es\n, N ew\nY or\nk C\nity , P\nue rt\no R\nic o,\nth e\nD is\ntr ic\nt o f\nC ol\num bi\na an d th e G re at P la in s T ri ba l C ha ir m en ’s H ea lth B oa rd th at c ol le ct d at a on m at er na l at tit ud es a nd e xp er ie nc es a nd is u se d to id en tif y gr ou ps o f w om en a nd in fa nt\ns at\nhi\ngh r\nis k\nfo r\nhe al\nth p\nro bl\nem s.\nSu rv\ney d\nes ig\nn: c\nro ss\n-s ec\ntio na\nl s ur\nve y\nof m\not he\nrs w\nho h\nav e\nre ce\nnt ly\ng iv\nen li\nve\nbi rt\nh, p\nop ul\nat io\nnba\nse d\n» 19\n88 –2\n01 6\n(o ng\noi ng\n): c\non tin\nuo us\nd at\na co\nlle ct\nio n\nbu t 8\np ha\nse s\nof q\nue st\nio nn\nai re\nco\nnt en\nt/d es\nig n\nch an\nge s\n(~ 4\nye ar\ns pe\nr ph\nas e)\n» R\nep re\nse nt\nat iv\ne of\ns ta\nte p\nop ul\nat io\nn an\nd 83\n% o\nf al\nl U .S . liv e bi rt hs » O ve rs am pl e of lo w w ei gh t b ir th s; in di vi du al s ta te s m ay st ra tif y by m ot he r’ s ra ce o r et hn ic ity » 1, 30 0– 3, 40 0 (a nn ua l s am pl e) » Su bgr ou p sa m pl e si ze s no t r ea di ly a va ila bl e\nD ’A\nng el\no D\nV , L\ne B\n, O ’N\nei l M\nE , e\nt a l.\nPa tte\nrn s\nof\nH ea\nlth I\nns ur\nan ce\nC ov\ner ag\ne A\nro un\nd th\ne T\nim e\nof\nPr eg\nna nc\ny A\nm on\ng W\nom en\nw ith\nL iv\neB\nor n\nIn fa\nnt s—\nPr eg\nna nc\ny R\nis k\nA ss\nes sm\nen t M\non ito\nri ng\nS ys\nte m\n, 2 9\nSt at\nes , 2\n00 9.\nA tla\nnt a,\nG A\n: C en\nte r\nfo r\nD is\nea se\nC on\ntr ol\nan\nd Pr\nev en\ntio n;\n2 01\n5.\nJ Health Care Poor Underserved. Author manuscript; available in PMC 2019 August 13.\nA uthor M anuscript A uthor M anuscript\nA uthor M anuscript A uthor M anuscript\nTa b\nle 3\n.\nA V\nA IL\nA B\nIL IT\nY O\nF M\nE A\nSU R\nE S\nB Y\nN A\nT IO\nN A\nL -L\nE V\nE L\nD A\nTA SE\nT S,\nU N\nIT E\nD S\nTA T\nE S,\n1 98\n7– 20\n17\nN at\nio na\nlle\nve l d\nat as\net s\nE C\nL S\nN L\nSY 7\nP SI\nD 7\nA C\nS A\ndd H\nea lt\nh1 A\nP S\nC P\nS2 B\nir th\n3 K\nin de\nr ga\nrt en\n4 F\nF C\nW S1\nN H\nA N\nE S2\nN H\nIS 5\nN IS\n6 79\n1 79\nC hi\nld /Y\nA 8\n97 9\nN SF\nG N\nSF H\n10 F\nog Z\non e\nM ai\nn2 C\nD S\nC D\nS 20\n14 T\nA S\nSI P\nP 11\nN V\nSS :\nB ir\nth\nD at\na1 2\nIm m\nig ra\ntio n\nN\nat iv\nity x\nx x\nx x\nx x\nx x\nx x\nx x\nx x\nxd xd\nx\nC\niti ze\nns hi\np x\nx x\nx x\nx x\nx x\nx x\nx\nC\nou nt\nry o\nr re\ngi on\no f\nbi rt\nh x\nx x\nx x\nx x\nx x\nx x\nx x\nL\nen gt\nh of\ns ta\ny x\nx x\nx\nY\nea r\nof e\nnt ry\nx x\nx x\nx x\nx x\nx x\nx x\nx\nL\nan gu\nag e\nsp ok\nen a\nt h om\ne x\nx x\nx x\nx x\nx x\nx x\nx x\nD\noc um\nen ta\ntio n\nx x\nx\nR ac\ne &\ne th\nni ci\nty\nR ac\ne\nA\nm er\nic an\nI nd\nia n/\nA la\nsk a\nN at\niv e\nx x\nx x\nx x\nx x\nx xb\nx x\nxb x\nx x\nx x\nx\nA\nsi an\nx xa\nx x\nx x\nxa x\nx x\nx x\nx xa\nx xa\nx x\nx x\nB\nla ck\n/A fr\nic an\nA m\ner ic\nan x\nx x\nx x\nx x\nx x\nx x\nx xc\nx x\nx x\nx x\nx\nN\nat iv\ne H\naw ai\nia n/\nPa ci\nfi c\nIs la\nnd er\nx xa\nx x\nx x\nxa x\nx x\nx x\nxa x\nxa x\nx x\nx\nW\nhi te\nx x\nx x\nx x\nx x\nx x\nx x\nx x\nx x\nx x\nx x\nE th\nni ci\nty\nN\nat iv\ne tr\nib e\nx x\nx\nA\nsi an\no ri\ngi n\nx x\nx x\nx x\nx x\nx x\nx x\nx x\nB\nla ck\n/A fr\nic an\no ri\ngi n\nx\nH\nis pa\nni c\nor ig\nin x\nx x\nx x\nx x\nx x\nx x\nx x\nx x\nx x\nx x\nx\nPa\nci fi\nc Is\nla nd\ner o\nri gi\nn x\nx x\nx x\nx x\nE\nur op\nea n\nor ig\nin x\nx x\nx\nA nc\nes tr\ny x\nx x\nx x\nx x\nSe xu\nal &\nr ep\nro du\nct iv\ne he\nal th\nPr\neg na\nnc y\nin te\nnt io\nns x\nx x\nx x\nx x\nx x\nx\nFe\nrt ili\nty h\nis to\nry x\nx x\nx x\nx x\nx x\nx x\nx x\nx x\nx x\nx x\nx x\nx\nC\non tr\nac ep\ntiv e\nus e\nx x\nx x\nx x\nx x\nx x\nx x\nx\nJ Health Care Poor Underserved. Author manuscript; available in PMC 2019 August 13.\nA uthor M anuscript A uthor M anuscript\nA uthor M anuscript A uthor M anuscript\nN at\nio na\nlle\nve l d\nat as\net s\nE C\nL S\nN L\nSY 7\nP SI\nD 7\nA C\nS A\ndd H\nea lt\nh1 A\nP S\nC P\nS2 B\nir th\n3 K\nin de\nr ga\nrt en\n4 F\nF C\nW S1\nN H\nA N\nE S2\nN H\nIS 5\nN IS\n6 79\n1 79\nC hi\nld /Y\nA 8\n97 9\nN SF\nG N\nSF H\n10 F\nog Z\non e\nM ai\nn2 C\nD S\nC D\nS 20\n14 T\nA S\nSI P\nP 11\nN V\nSS :\nB ir\nth\nD at\na1 2\nH\nIV /S\nT I\nhi st\nor y\nx x\nx x\nx x\nx x\nSe\nxu al\nb eh\nav io\nr x\nx x\nx x\nx x\nx x\nx x\nSe\nxu al\no ri\nen ta\ntio n\nx x\nx x\nH ea\nlth s\ner vi\nce u\ntil iz\nat io\nn\nH\nea lth\nin su\nra nc\ne st\nat us\nx x\nx x\nx x\nx x\nx x\nx x\nx x\nx x\nx x\nx x\nSo\nur ce\no f\nca re\nx x\nx x\nx x\nx x\nN ot\nes\na ‘ A\nsi an\n’ an\nd ‘P\nac if\nic I\nsl an\nde r’\ng ro\nup ed\nto ge\nth er\nb ‘ A\nla sk\na N\nat iv\ne’ n\not in\ncl ud\ned\nc I nc\nlu de\ns ‘B\nla ck\n’ on\nly\nd R es\npo nd\nen t’\ns na\ntiv ity\nm ay\nb e\nco ns\ntr uc\nte d\nfr om\nr es\npo nd\nen t’\ns bi\nrt h\nm on\nth /y\nea r\nan d\nm ot\nhe r’\ns im\nm ig\nra tio\nn va\nri ab\nle s\n(n at\niv ity\n, m on\nth /y\nea r\nof e\nnt ry\n) fr\nom P\nSI D\n-m ai\nn\n1 R es\npo nd\nen t’\ns pa\nre nt\nd at\na av\nai la\nbl e\nfo r\nna tiv\nity a\nnd c\nou nt\nry o\nr re\ngi on\no f\nbi rt\nh m\nea su\nre s.\n2 R es\npo nd\nen t’\ns pa\nre nt\nd at\na av\nai la\nbl e\nfo r\nco un\ntr y\nor r\neg io\nn of\nb ir\nth m\nea su\nre s.\n3 E C\nL S-\nB ir\nth c\nol le\nct ed\nd at\na on\na c\noh or\nt o f\nch ild\nre n\nfr om\nb ir\nth to\nk in\nde rg\nar te\nn. C\nhi ld\n’s d\nat a\nav ai\nla bl\ne fo\nr lim\nite d\nra ce\nm ea\nsu re\ns an\nd na\ntiv e\ntr ib\ne, A\nsi an\no ri\ngi n,\nH is\npa ni\nc or\nig in\n, a nd\nP ac\nif ic\nI sl\nan de\nr or\nig in\n. I nf\nor m\nat io\nn di\nsp la\nye d\nhe re\nis a\nva ila\nbl e\nda ta\nf or\nc hi\nld ’s\np ar\nen t w\nho a\nns w\ner ed\nth\ne su\nrv ey\n.\n4 R es\npo nd\nen t’\ns pa\nre nt\nd at\na av\nai la\nbl e\nfo r\nci tiz\nen sh\nip , c\nou nt\nry o\nr re\ngi on\no f\nbi rt\nh, la\nng ua\nge s\npo ke\nn at\nh om\ne, a\nll C\nD C\nr ac\ne ca\nte go\nri es\n, a nd\nH is\npa ni\nc or\nig in\nm ea\nsu re\ns.\n5 S pe\nci al\np op\nul at\nio n\nfo cu\ns on\nN at\niv e\nH aw\nai ia\nn an\nd Pa\nci fi\nc Is\nla nd\ner a\nva ila\nbl e\nw ith\n2 01\n6 da\nta r\nel ea\nse . A\ndd iti\non al\nH is\npa ni\nc, A\nsi an\na nd\nN at\niv e\nH aw\nai ia\nn or\nP ac\nif ic\nI sl\nan de\nr an\nce st\nry /o\nri gi\nn w\nill b\ne ad\nde d\nin 2\n01 8.\n6 R es\npo nd\nen t’\ns pa\nre nt\nd at\na av\nai la\nbl e\nfo r\nci tiz\nen sh\nip , c\nou nt\nry o\nr re\ngi on\no f\nbi rt\nh, a\nnd y\nea r\nof e\nnt ry\nm ea\nsu re\ns.\n7 C hi\nld to\nm ot\nhe r\nlin ka\nge p\nos si\nbl e.\nN L\nSY 79\nC hi\nld /Y\nA d\nat as\net c\nan b\ne lin\nke d\nto m\not he\nr’ s\nda ta\nin o\nri gi\nna l N\nL SY\n79 . P\nSI D\n-C D\nS an\nd PS\nID -T\nA S\nda ta\nse ts\nc an\nb e\nlin ke\nd to\nm ot\nhe r’\ns da\nta in\nP SI\nD -m\nai n.\n8 R es\npo nd\nen t’\ns pa\nre nt\nd at\na av\nai la\nbl e\nfo r\nna tiv\nity , c\nou nt\nry o\nr re\ngi on\no f\nbi rt\nh, a\nnd a\nll C\nD C\nr ac\ne m\nea su\nre s.\n9 R es\npo nd\nen t’\ns pa\nre nt\nd at\na av\nai la\nbl e\nfo r\nna tiv\nity , c\niti ze\nns hi\np, c\nou nt\nry o\nr re\ngi on\no f\nbi rt\nh, la\nng ua\nge s\npo ke\nn at\nh om\ne, A\nsi an\no ri\ngi n,\nH is\npa ni\nc or\nig in\n, a nd\nE ur\nop ea\nn or\nig in\n.\n10 R\nes po\nnd en\nt’ s\npa re\nnt d\nat a\nav ai\nla bl\ne fo\nr na\ntiv ity\nm ea\nsu re\n. R es\npo nd\nen t’\ns ch\nild d\nat a\nav ai\nla bl\ne fo\nr pr\neg na\nnc y\nin te\nnt io\nns , f\ner til\nity h\nis to\nry , a\nnd s\nex ua\nl b eh\nav io\nr m\nea su\nre s.\n11 R\nes po\nnd en\nt’ s\npa re\nnt d\nat a\nav ai\nla bl\ne fo\nr ci\ntiz en\nsh ip\nm ea\nsu re\n. S ta\nrt in\ng in\n2 01\n4 pa\nne l,\npa re\nnt ’s\nn at\niv ity\na nd\nc ou\nnt ry\no f\nbi rt\nh w\nill b\ne ad\nde d,\na s\nw el\nl a s\nye ar\no f\nen tr\ny fo\nr re\nsp on\nde nt\n.\n12 N\nV SS\n: B ir\nth D\nat a\nco m\nes f\nro m\nb ir\nth c\ner tif\nic at\ne da\nta in\nth e\nU ni\nte d\nSt at\nes . C\nhi ld\nre n\nfr om\nth is\nd at\na ar\ne U\n.S . c\niti ze\nns . I\nnf or\nm at\nio n\ndi sp\nla ye\nd he\nre is\na va\nila bl\ne da\nta f\nor c\nhi ld\n’s p\nar en\nt w ho\na ns\nw er\ned th\ne su\nrv ey\n.\nJ Health Care Poor Underserved. Author manuscript; available in PMC 2019 August 13.\nA uthor M anuscript A uthor M anuscript\nA uthor M anuscript A uthor M anuscript\nTapales et al. Page 21 A C S = A m er ic an C om m un ity S ur ve y A PS = A bo rt io n Pa tie nt S ur ve y C PS = C ur re nt P op ul at io n Su rv ey E C L S = E ar ly C hi ld ho od L on gi tu di na l S tu dy FF C W S = F ra gi le F am ili es a nd C hi ld W el lb ei ng S tu dy N H A N E S = N at io na l H ea lth a nd N ut ri tio n E xa m in at io n Su rv ey N H IS = N at io na l H ea lth I nt er vi ew S ur ve y N IS = N ew I m m ig ra nt S ur ve y N L SY = N at io na l L on gi tu di na l S ur ve y of Y ou th N SF G = N at io na l S ur ve y of F am ily G ro w th N SF H = N at io na l S ur ve y of F am ili es a nd H ou se ho ld s PS ID = P an el S tu dy o f In co m e D yn am ic s C D S = C hi ld D ev el op m en t S ur ve y TA S = T ra ns iti on to A du lth oo d Su pp le m en t SI PP = S ur ve y of I nc om e an d Pr og ra m P ar tic ip at io n N V SS = N at io na l V ita l S ta tis tic s Sy st em\nJ Health Care Poor Underserved. Author manuscript; available in PMC 2019 August 13.\nA uthor M anuscript A uthor M anuscript\nA uthor M anuscript A uthor M anuscript\nTable 4.\nAVAILABILITY OF MEASURES BY STATE- OR COUNTY-LEVEL DATASETS, UNITED STATES, 1987–2017\nState- or county-level datasets\nBCAS 1 CHIS CWHS LACHS MIHA NYCCHS 2 PRAMS 3\nImmigration\nNativity x x x x\nCitizenship x x\nCountry or region of birth x x x x x\nLength of stay x x x x x\nYear of entry x\nLanguage spoken at home x x x x x\nDocumentation x\nRace & ethnicity\nRace\nAmerican Indian/Alaska Native x b x x x x\nAsian x x x x x a x x\nBlack/African American x x x x x x x\nNative Hawaiian/Pacific Islander x x x c\nx a x xd\nWhite x x x x x x x\nEthnicity\nAsian origin x x x x x\nBlack/African origin x\nHispanic origin x x x x x x x\nPacific Islander origin x x\nEuropean origin\nAncestry x x x\nSexual & reproductive health\nPregnancy intentions x x x x x\nFertility history x x x x\nContraceptive use x x x x x x\nHIV/STI history x x x x\nSexual behavior x x x x x\nSexual orientation x x x\nHealth service utilization\nHealth insurance status x x x x x\nSource of care x x x x x\nNotes\na ‘Asian’ and ‘Pacific Islander’ grouped together\nb ‘Alaska Native’ not included\nJ Health Care Poor Underserved. Author manuscript; available in PMC 2019 August 13.\nA uthor M anuscript A uthor M anuscript\nA uthor M anuscript A uthor M anuscript\nc Includes ‘Pacific Islander’ only\nd Includes ‘Native Hawaiian’ only\n1 Respondent’s parent data available for nativity and length of stay measures. Respondent’s child data available for nativity and length of stay measures.\n2 Respondent’s parent data available for nativity measure.\n3 Respondent’s data for nativity, year of entry, language spoken at home, Hispanic origin, and Pacific Islander origin measures are only included in Phase 6 (2009–2011) core questions. For other years and other additional data from National Vital Statistics System - Birth can be requested to be linked and included through state coordinators.\nBCAS= Border Contraceptive Access Study\nCHIS= California Health Interview Survey\nCWHS= California Women’s Health Survey\nLACHS= LA County Health Survey\nMIHA= Maternal Infant Health Assessment\nNYCCHS= New York City Community Health Survey\nPRAMS= Pregnancy Risk Assessment Monitoring System\nJ Health Care Poor Underserved. Author manuscript; available in PMC 2019 August 13."
    } ],
    "references" : [ {
      "title" : "Modern immigration wave brings 59 million to U.S., driving population growth and change through 2065",
      "author" : [ "Pew Research Center" ],
      "venue" : "Pew Research Center,",
      "citeRegEx" : "1",
      "shortCiteRegEx" : "1",
      "year" : 2015
    }, {
      "title" : "The foreign-born population in the United States: 2010. Washington, DC: U.S",
      "author" : [ "EM Grieco", "YD Acosta", "GP de la Cruz" ],
      "venue" : "Census Bureau,",
      "citeRegEx" : "3",
      "shortCiteRegEx" : "3",
      "year" : 2012
    }, {
      "title" : "Disparities in public use data availability for race, ethnic, and immigrant groups: national surveys for healthcare disparities research",
      "author" : [ "PJ Johnson", "LA Blewett", "M. Davern" ],
      "venue" : "Med Care",
      "citeRegEx" : "4",
      "shortCiteRegEx" : "4",
      "year" : 2010
    }, {
      "title" : "Methodological issues in the collection, analysis, and reporting of granular data in Asian American populations: historical challenges and potential solutions",
      "author" : [ "NS Islam", "S Khan", "S Kwon" ],
      "venue" : "J Health Care Poor Underserved",
      "citeRegEx" : "5",
      "shortCiteRegEx" : "5",
      "year" : 2010
    }, {
      "title" : "Advancing the field of public health surveillance and survey methods",
      "author" : [ "Lau DT" ],
      "venue" : "Am J Public Health",
      "citeRegEx" : "6",
      "shortCiteRegEx" : "6",
      "year" : 2017
    }, {
      "title" : "Out of the shadows: Asian Americans, Native Hawaiians, and Pacific Islanders",
      "author" : [ "Ro MJ", "Yee AK" ],
      "venue" : "Am J Public Health",
      "citeRegEx" : "7",
      "shortCiteRegEx" : "7",
      "year" : 2010
    }, {
      "title" : "Health status and access to care In: National Academies of Sciences, Engineering, and Medicine. The Integration of immigrants into American society",
      "author" : [ "MC Waters", "MG Pineau", "eds" ],
      "venue" : null,
      "citeRegEx" : "8",
      "shortCiteRegEx" : "8",
      "year" : 2015
    }, {
      "title" : "Review: immigrants and health care access, quality, and cost",
      "author" : [ "KP Derose", "BW Bahney", "N Lurie" ],
      "venue" : "Med Care Res Rev",
      "citeRegEx" : "9",
      "shortCiteRegEx" : "9",
      "year" : 2009
    }, {
      "title" : "Improving public health surveillance about Asian Americans, Native Hawaiians, and Pacific Islanders",
      "author" : [ "Chin KK" ],
      "venue" : "Am J Public Health",
      "citeRegEx" : "10",
      "shortCiteRegEx" : "10",
      "year" : 2017
    }, {
      "title" : "Structural racism and health inequities: old issues, new directions",
      "author" : [ "Gee GC", "Ford CL" ],
      "venue" : "Du Bois Rev. 2011 4;8(1):115–32",
      "citeRegEx" : "11",
      "shortCiteRegEx" : "11",
      "year" : 2011
    }, {
      "title" : "Health insurance coverage among foreign-born US residents: the impact of race, ethnicity, and length of residence",
      "author" : [ "M Thamer", "C Richard", "AW Casebeer" ],
      "venue" : "Am J Public Health",
      "citeRegEx" : "12",
      "shortCiteRegEx" : "12",
      "year" : 1997
    }, {
      "title" : "Asian American women in California: a pooled analysis of predictors for breast and cervical cancer screening",
      "author" : [ "N Chawla", "N Breen", "B Liu" ],
      "venue" : "Am J Public Health. 2015 2;105(2):e98–109",
      "citeRegEx" : "13",
      "shortCiteRegEx" : "13",
      "year" : 2014
    }, {
      "title" : "Fertility of Mexican immigrant women in the U.S.: a closer look",
      "author" : [ "M Carter" ],
      "venue" : "Soc Sci Q",
      "citeRegEx" : "14",
      "shortCiteRegEx" : "14",
      "year" : 2000
    }, {
      "title" : "Barriers to health care among Asian immigrants in the United States: a traditional review",
      "author" : [ "J Clough", "S Lee", "DH. Chae" ],
      "venue" : "J Health Care Poor Underserved",
      "citeRegEx" : "15",
      "shortCiteRegEx" : "15",
      "year" : 2013
    }, {
      "title" : "Serving Asians and Pacific Islanders with HIV/AIDS: challenges and lessons learned",
      "author" : [ "JJ Chin", "E Kang", "JH Kim" ],
      "venue" : "J Health Care Poor Underserved",
      "citeRegEx" : "16",
      "shortCiteRegEx" : "16",
      "year" : 2006
    }, {
      "title" : "Differences in low-birthweight among documented and undocumented foreign-born and US-born Latinas",
      "author" : [ "Kelaher M", "Jessop DJ" ],
      "venue" : "Soc Sci Med",
      "citeRegEx" : "17",
      "shortCiteRegEx" : "17",
      "year" : 2002
    }, {
      "title" : "Prenatal care among immigrant and racial-ethnic minority women in a new immigrant destination: exploring the impact of immigrant legal status",
      "author" : [ "Korinek K", "Smith KR" ],
      "venue" : "Soc Sci Med",
      "citeRegEx" : "18",
      "shortCiteRegEx" : "18",
      "year" : 2011
    }, {
      "title" : "Racial and ethnic disparities in cancer screening",
      "author" : [ "MS Goel", "CC Wee", "EP McCarthy" ],
      "venue" : "J Gen Intern Med",
      "citeRegEx" : "19",
      "shortCiteRegEx" : "19",
      "year" : 2003
    }, {
      "title" : "Breast and cervical cancer screening rates of subgroups of Asian American women in California",
      "author" : [ "M Kagawa-Singer", "N Pourat", "N Breen" ],
      "venue" : "Med Care Res Rev",
      "citeRegEx" : "20",
      "shortCiteRegEx" : "20",
      "year" : 2007
    }, {
      "title" : "Cervical cancer screening among foreign-born women by birthplace and duration in the United States",
      "author" : [ "J Tsui", "M Saraiya", "T Thompson" ],
      "venue" : "J Womens Health (Larchmt)",
      "citeRegEx" : "21",
      "shortCiteRegEx" : "21",
      "year" : 2007
    }, {
      "title" : "Population Center. National longitudinal study of adolescent to adult health (Add Health) [codebook explorer",
      "author" : [ "UNC Carolina" ],
      "venue" : "Chapel Hill, NC: University of North Carolina,",
      "citeRegEx" : "30",
      "shortCiteRegEx" : "30",
      "year" : 2008
    }, {
      "title" : "Current Population Survey (CPS) [questionnaire and dataferrett]. Washington, DC: U.S. Census Bureau, 2016 Available at: https://www.census.gov/programs-surveys/cps/ technical-documentation/questionnaires.html",
      "author" : [ "U.S. Census Bureau" ],
      "venue" : null,
      "citeRegEx" : "35",
      "shortCiteRegEx" : "35",
      "year" : 2016
    }, {
      "title" : "American Community Survey (ACS) [questionnaire and American FactFinder]. Washington, DC: U.S",
      "author" : [ "U.S. Census Bureau" ],
      "venue" : "Census Bureau,",
      "citeRegEx" : "37",
      "shortCiteRegEx" : "37",
      "year" : 2015
    }, {
      "title" : "County Department of Public Health. Los Angeles County Health Survey (LACHS) [questionnaire and methodology report",
      "author" : [ "Los Angeles" ],
      "venue" : "Los Angeles, CA: Los Angeles County Department of Public Health,",
      "citeRegEx" : "42",
      "shortCiteRegEx" : "42",
      "year" : 2011
    }, {
      "title" : "Border Contraceptive Access Study (BCAS) [questionnaire and codebook",
      "author" : [ "JE Potter", "K Hopkins", "J Amastae" ],
      "venue" : "Ann Arbor, MI: University of Michigan,",
      "citeRegEx" : "43",
      "shortCiteRegEx" : "43",
      "year" : 2006
    }, {
      "title" : "Survey of Income and Program Participation [questionnaire]. Washington, DC: U.S",
      "author" : [ "U.S. Census Bureau" ],
      "venue" : "Census Bureau,",
      "citeRegEx" : "52",
      "shortCiteRegEx" : "52",
      "year" : 2008
    }, {
      "title" : "Challenges to surveying immigrants",
      "author" : [ "Massey DS" ],
      "venue" : "10.1017/CBO9781139381635.017",
      "citeRegEx" : "53",
      "shortCiteRegEx" : "53",
      "year" : 2014
    }, {
      "title" : "A demographic, socioeconomic and health coverage profile of unauthorized immigrants in the United States",
      "author" : [ "R Capps", "M Fix", "J van Hook" ],
      "venue" : "Migration Policy Institute,",
      "citeRegEx" : "54",
      "shortCiteRegEx" : "54",
      "year" : 2013
    }, {
      "title" : "Asian American communities and health: context, research, policy, and action (1st ed.)",
      "author" : [ "C Trinh-Shevrin", "NS Islam", "MJ Rey", "eds" ],
      "venue" : null,
      "citeRegEx" : "55",
      "shortCiteRegEx" : "55",
      "year" : 2009
    }, {
      "title" : "Influences of culture on Asian Americans",
      "author" : [ "S Okazaki" ],
      "venue" : "sexuality. J Sex Res",
      "citeRegEx" : "56",
      "shortCiteRegEx" : "56",
      "year" : 2002
    }, {
      "title" : "Community-based participatory research approach to evidence-based research: lessons from the Pacific Islander American Health Study",
      "author" : [ "S Panapasa", "J Jackson", "C Caldwell" ],
      "venue" : "Prog Community Health Partnersh. 2012 Spring;6(1):53–8",
      "citeRegEx" : "57",
      "shortCiteRegEx" : "57",
      "year" : 2012
    } ],
    "referenceMentions" : [ {
      "referenceID" : 0,
      "context" : "This review focuses on the following six SRH domains, each representing multiple measures of SRH: (1) pregnancy intention (i.",
      "startOffset" : 98,
      "endOffset" : 101
    }, {
      "referenceID" : 1,
      "context" : ", number of births or children, maternal age at first birth, history of abortion, and other pregnancy outcomes), (3) contraceptive use (e.",
      "startOffset" : 113,
      "endOffset" : 116
    }, {
      "referenceID" : 2,
      "context" : ", current method(s) used and history of method use), (4) HIV/STI history (e.",
      "startOffset" : 53,
      "endOffset" : 56
    }, {
      "referenceID" : 3,
      "context" : ", history of HIV/STI testing or treatment, HPV vaccination, and STI diagnoses), (5) sexual behavior (e.",
      "startOffset" : 80,
      "endOffset" : 83
    }, {
      "referenceID" : 4,
      "context" : ", age at first sexual encounter, timing of last sexual encounter, and other information about sexual encounters), and (6) sexual orientation.",
      "startOffset" : 118,
      "endOffset" : 121
    }, {
      "referenceID" : 0,
      "context" : "We also identified seven examples of (1) state-level data from New York and California (Pregnancy Risk Assessment Monitoring System [PRAMS],38 California Health Interview Survey [CHIS]39, California Women’s Health Survey [CWHS],40 and California Maternal Infant Health Assessment [MIHA]41); (2) county-level data from Los Angeles (LA County Health Survey [LACHS]42); and (3) city-level data from El Paso (Border Contraceptive Access Study [BCAS]43) and New York City (New York City Community Health Survey [NYCCHS]44) (Table 2).",
      "startOffset" : 37,
      "endOffset" : 40
    }, {
      "referenceID" : 1,
      "context" : "We also identified seven examples of (1) state-level data from New York and California (Pregnancy Risk Assessment Monitoring System [PRAMS],38 California Health Interview Survey [CHIS]39, California Women’s Health Survey [CWHS],40 and California Maternal Infant Health Assessment [MIHA]41); (2) county-level data from Los Angeles (LA County Health Survey [LACHS]42); and (3) city-level data from El Paso (Border Contraceptive Access Study [BCAS]43) and New York City (New York City Community Health Survey [NYCCHS]44) (Table 2).",
      "startOffset" : 371,
      "endOffset" : 374
    }, {
      "referenceID" : 2,
      "context" : "2010 11;21(4):1354–81 [PubMed: 21099084] 6.",
      "startOffset" : 10,
      "endOffset" : 13
    } ],
    "year" : 2019,
    "abstractText" : "This paper aims to identify, review, and evaluate publicly available nationaland local-level data sources that collect information on the sexual and reproductive health (SRH) of immigrants in the United States. We review public-use sources from the last 30 years that include information on immigration, SRH, health service utilization, and race/ethnicity. For each source, we evaluated the strengths and challenges of the study design and content as they relate to studying immigrant SRH. We identified and reviewed 22 national and seven local sources. At the national level, the National Longitudinal Study of Adolescent to Adult Health and the National Survey of Family Growth contained the most information; at the local level, the New York City Community Health Survey was the most robust. These sources present opportunities to advance research, improve public health surveillance, and inform policies and programs related to the SRH of this rapidly growing and often underserved population.",
    "creator" : "AH XSL Formatter V6.3 R1 for Linux64 : 6.3.1.23495 (2016/02/03 14:39JST)"
  }
}